Workbook

Sheet Dashboard
A1: Netflix catalogue dashboard (public Netflix titles dataset)
A3: Titles | C3: Movie share | E3: Avg movie (min)
A4: =Analysis!B3 -> 6234 | C4: =Analysis!B6 -> 0.68415143 | E4: =Analysis!B7 -> 99.100821
A6: Key findings (live formulas)
A7: ="Peak year: "&INDEX(Analysis!A14:A26,MATCH(MAX(Analysis!D14:D26),Analysis!D14:D26,0))&" saw the most additions ("&TEXT(MAX(Analysis!D14:D26),"#,##0")&" titles)." -> Peak year: 2019 saw the most additions (2,349 titles).
A8: ="Mix: "&TEXT(Analysis!B6,"0%")&" of the catalogue is movies; the average movie runs "&TEXT(Analysis!B7,"0")&" minutes." -> Mix: 68% of the catalogue is movies; the average movie runs 99 minutes.
A9: ="Top country: "&Analysis!A31&" with "&TEXT(Analysis!C31,"0.0%")&" of all titles." -> Top country: United States with 36.9% of all titles.
A10: ="Top genre: "&Analysis!A45&" ("&TEXT(Analysis!C45,"0.0%")&")." -> Top genre: Dramas (17.3%).

Sheet Analysis
A1: Netflix catalogue analysis (cleaning done with formulas on the Data sheet)
D2: Cleaning log: missing values
A3: Titles | B3: =COUNTA(Data!$A$2:$A$6235) -> 6234 | D3: Column | E3: Blank cells | F3: % of titles
A4: Movies | B4: =COUNTIF(Data!$B$2:$B$6235,"Movie") -> 4265 | D4: director | E4: =COUNTBLANK(Data!$D$2:$D$6235) -> 1969 | F4: =IFERROR(E4/$B$3,0) -> 0.31584857
A5: TV shows | B5: =COUNTIF(Data!$B$2:$B$6235,"TV Show") -> 1969 | D5: country | E5: =COUNTBLANK(Data!$E$2:$E$6235) -> 476 | F5: =IFERROR(E5/$B$3,0) -> 0.07635547
A6: Movie share | B6: =IFERROR(B4/B3,0) -> 0.68415143 | D6: date_added | E6: =COUNTBLANK(Data!$F$2:$F$6235) -> 11 | F6: =IFERROR(E6/$B$3,0) -> 0.0017645172
A7: Avg movie length (min) | B7: =AVERAGE(Data!$N$2:$N$6235) -> 99.100821 | D7: rating | E7: =COUNTBLANK(Data!$H$2:$H$6235) -> 10 | F7: =IFERROR(E7/$B$3,0) -> 0.0016041065
A8: Avg TV seasons | B8: =AVERAGE(Data!$O$2:$O$6235) -> 1.7795835
A9: Avg years from release to added | B9: =AVERAGE(Data!$P$2:$P$6235) -> 4.6210831 | D9: Blank countries are labelled "Unknown"; rows with no date_added are left out of the year trend.
A12: Titles added per year
A13: Year | B13: Movies | C13: TV shows | D13: Total
A14: 2008 | B14: =COUNTIFS(Data!$K$2:$K$6235,$A14,Data!$B$2:$B$6235,"Movie") -> 1 | C14: =COUNTIFS(Data!$K$2:$K$6235,$A14,Data!$B$2:$B$6235,"TV Show") -> 1 | D14: =B14+C14 -> 2
A15: 2009 | B15: =COUNTIFS(Data!$K$2:$K$6235,$A15,Data!$B$2:$B$6235,"Movie") -> 2 | C15: =COUNTIFS(Data!$K$2:$K$6235,$A15,Data!$B$2:$B$6235,"TV Show") -> 0 | D15: =B15+C15 -> 2
A16: 2010 | B16: =COUNTIFS(Data!$K$2:$K$6235,$A16,Data!$B$2:$B$6235,"Movie") -> 1 | C16: =COUNTIFS(Data!$K$2:$K$6235,$A16,Data!$B$2:$B$6235,"TV Show") -> 0 | D16: =B16+C16 -> 1
A17: 2011 | B17: =COUNTIFS(Data!$K$2:$K$6235,$A17,Data!$B$2:$B$6235,"Movie") -> 13 | C17: =COUNTIFS(Data!$K$2:$K$6235,$A17,Data!$B$2:$B$6235,"TV Show") -> 0 | D17: =B17+C17 -> 13
A18: 2012 | B18: =COUNTIFS(Data!$K$2:$K$6235,$A18,Data!$B$2:$B$6235,"Movie") -> 4 | C18: =COUNTIFS(Data!$K$2:$K$6235,$A18,Data!$B$2:$B$6235,"TV Show") -> 3 | D18: =B18+C18 -> 7
A19: 2013 | B19: =COUNTIFS(Data!$K$2:$K$6235,$A19,Data!$B$2:$B$6235,"Movie") -> 6 | C19: =COUNTIFS(Data!$K$2:$K$6235,$A19,Data!$B$2:$B$6235,"TV Show") -> 6 | D19: =B19+C19 -> 12
A20: 2014 | B20: =COUNTIFS(Data!$K$2:$K$6235,$A20,Data!$B$2:$B$6235,"Movie") -> 19 | C20: =COUNTIFS(Data!$K$2:$K$6235,$A20,Data!$B$2:$B$6235,"TV Show") -> 6 | D20: =B20+C20 -> 25
A21: 2015 | B21: =COUNTIFS(Data!$K$2:$K$6235,$A21,Data!$B$2:$B$6235,"Movie") -> 58 | C21: =COUNTIFS(Data!$K$2:$K$6235,$A21,Data!$B$2:$B$6235,"TV Show") -> 32 | D21: =B21+C21 -> 90
A22: 2016 | B22: =COUNTIFS(Data!$K$2:$K$6235,$A22,Data!$B$2:$B$6235,"Movie") -> 264 | C22: =COUNTIFS(Data!$K$2:$K$6235,$A22,Data!$B$2:$B$6235,"TV Show") -> 192 | D22: =B22+C22 -> 456
A23: 2017 | B23: =COUNTIFS(Data!$K$2:$K$6235,$A23,Data!$B$2:$B$6235,"Movie") -> 913 | C23: =COUNTIFS(Data!$K$2:$K$6235,$A23,Data!$B$2:$B$6235,"TV Show") -> 387 | D23: =B23+C23 -> 1300
A24: 2018 | B24: =COUNTIFS(Data!$K$2:$K$6235,$A24,Data!$B$2:$B$6235,"Movie") -> 1290 | C24: =COUNTIFS(Data!$K$2:$K$6235,$A24,Data!$B$2:$B$6235,"TV Show") -> 492 | D24: =B24+C24 -> 1782
A25: 2019 | B25: =COUNTIFS(Data!$K$2:$K$6235,$A25,Data!$B$2:$B$6235,"Movie") -> 1546 | C25: =COUNTIFS(Data!$K$2:$K$6235,$A25,Data!$B$2:$B$6235,"TV Show") -> 803 | D25: =B25+C25 -> 2349
A26: 2020 | B26: =COUNTIFS(Data!$K$2:$K$6235,$A26,Data!$B$2:$B$6235,"Movie") -> 147 | C26: =COUNTIFS(Data!$K$2:$K$6235,$A26,Data!$B$2:$B$6235,"TV Show") -> 37 | D26: =B26+C26 -> 184
A29: Top 10 primary countries
A30: Category | B30: Titles | C30: Share of titles
A31: United States | B31: =COUNTIF(Data!$L$2:$L$6235,$A31) -> 2302 | C31: =IFERROR(B31/$B$3,0) -> 0.36926532
A32: India | B32: =COUNTIF(Data!$L$2:$L$6235,$A32) -> 808 | C32: =IFERROR(B32/$B$3,0) -> 0.12961181
A33: United Kingdom | B33: =COUNTIF(Data!$L$2:$L$6235,$A33) -> 483 | C33: =IFERROR(B33/$B$3,0) -> 0.077478345
A34: Canada | B34: =COUNTIF(Data!$L$2:$L$6235,$A34) -> 206 | C34: =IFERROR(B34/$B$3,0) -> 0.033044594
A35: Japan | B35: =COUNTIF(Data!$L$2:$L$6235,$A35) -> 184 | C35: =IFERROR(B35/$B$3,0) -> 0.02951556
A36: France | B36: =COUNTIF(Data!$L$2:$L$6235,$A36) -> 147 | C36: =IFERROR(B36/$B$3,0) -> 0.023580366
A37: South Korea | B37: =COUNTIF(Data!$L$2:$L$6235,$A37) -> 146 | C37: =IFERROR(B37/$B$3,0) -> 0.023419955
A38: Spain | B38: =COUNTIF(Data!$L$2:$L$6235,$A38) -> 139 | C38: =IFERROR(B38/$B$3,0) -> 0.022297081
A39: Mexico | B39: =COUNTIF(Data!$L$2:$L$6235,$A39) -> 99 | C39: =IFERROR(B39/$B$3,0) -> 0.015880654
A40: Australia | B40: =COUNTIF(Data!$L$2:$L$6235,$A40) -> 94 | C40: =IFERROR(B40/$B$3,0) -> 0.015078601
A43: Top 10 primary genres
A44: Category | B44: Titles | C44: Share of titles
A45: Dramas | B45: =COUNTIF(Data!$M$2:$M$6235,$A45) -> 1077 | C45: =IFERROR(B45/$B$3,0) -> 0.17276227
A46: Comedies | B46: =COUNTIF(Data!$M$2:$M$6235,$A46) -> 803 | C46: =IFERROR(B46/$B$3,0) -> 0.12880975
A47: Documentaries | B47: =COUNTIF(Data!$M$2:$M$6235,$A47) -> 644 | C47: =IFERROR(B47/$B$3,0) -> 0.10330446
A48: Action & Adventure | B48: =COUNTIF(Data!$M$2:$M$6235,$A48) -> 597 | C48: =IFERROR(B48/$B$3,0) -> 0.095765159
A49: International TV Shows | B49: =COUNTIF(Data!$M$2:$M$6235,$A49) -> 570 | C49: =IFERROR(B49/$B$3,0) -> 0.091434071
A50: Children & Family Movies | B50: =COUNTIF(Data!$M$2:$M$6235,$A50) -> 358 | C50: =IFERROR(B50/$B$3,0) -> 0.057427013
A51: Crime TV Shows | B51: =COUNTIF(Data!$M$2:$M$6235,$A51) -> 309 | C51: =IFERROR(B51/$B$3,0) -> 0.049566891
A52: Kids' TV | B52: =COUNTIF(Data!$M$2:$M$6235,$A52) -> 288 | C52: =IFERROR(B52/$B$3,0) -> 0.046198268
A53: Stand-Up Comedy | B53: =COUNTIF(Data!$M$2:$M$6235,$A53) -> 273 | C53: =IFERROR(B53/$B$3,0) -> 0.043792108
A54: British TV Shows | B54: =COUNTIF(Data!$M$2:$M$6235,$A54) -> 210 | C54: =IFERROR(B54/$B$3,0) -> 0.033686237
A57: Content ratings
A58: Category | B58: Titles | C58: Share of titles
A59: TV-MA | B59: =COUNTIF(Data!$H$2:$H$6235,$A59) -> 2027 | C59: =IFERROR(B59/$B$3,0) -> 0.32515239
A60: TV-14 | B60: =COUNTIF(Data!$H$2:$H$6235,$A60) -> 1698 | C60: =IFERROR(B60/$B$3,0) -> 0.27237729
A61: TV-PG | B61: =COUNTIF(Data!$H$2:$H$6235,$A61) -> 701 | C61: =IFERROR(B61/$B$3,0) -> 0.11244787
A62: R | B62: =COUNTIF(Data!$H$2:$H$6235,$A62) -> 508 | C62: =IFERROR(B62/$B$3,0) -> 0.081488611
A63: PG-13 | B63: =COUNTIF(Data!$H$2:$H$6235,$A63) -> 286 | C63: =IFERROR(B63/$B$3,0) -> 0.045877446
A64: NR | B64: =COUNTIF(Data!$H$2:$H$6235,$A64) -> 218 | C64: =IFERROR(B64/$B$3,0) -> 0.034969522
A65: PG | B65: =COUNTIF(Data!$H$2:$H$6235,$A65) -> 184 | C65: =IFERROR(B65/$B$3,0) -> 0.02951556
A66: TV-Y7 | B66: =COUNTIF(Data!$H$2:$H$6235,$A66) -> 169 | C66: =IFERROR(B66/$B$3,0) -> 0.0271094

Sheet Data
A1: show_id | B1: type | C1: title | D1: director | E1: country | F1: date_added | G1: release_year | H1: rating | I1: duration | J1: listed_in | K1: Year added | L1: Primary country | M1: Primary genre | N1: Movie minutes | O1: TV seasons | P1: Years to add
A2: 81145628 | B2: Movie | C2: Norm of the North: King Sized Adventure | D2: Richard Finn, Tim Maltby | E2: United States, India, South Korea, China | F2: September 9, 2019 | G2: 2019 | H2: TV-PG | I2: 90 min | J2: Children & Family Movies, Comedies | K2: =IFERROR(VALUE(RIGHT(TRIM(F2),4)),"") -> 2019 | L2: =IF(TRIM(E2)="","Unknown",IFERROR(LEFT(TRIM(E2),FIND(",",TRIM(E2))-1),TRIM(E2))) -> United States | M2: =IFERROR(LEFT(J2,FIND(",",J2)-1),J2) -> Children & Family Movies | N2: =IF(B2="Movie",IFERROR(VALUE(LEFT(I2,FIND(" ",I2)-1)),""),"") -> 90 | O2: =IF(B2="TV Show",IFERROR(VALUE(LEFT(I2,FIND(" ",I2)-1)),""),"") | P2: =IF(K2="","",K2-G2) -> 0
A3: 80117401 | B3: Movie | C3: Jandino: Whatever it Takes | E3: United Kingdom | F3: September 9, 2016 | G3: 2016 | H3: TV-MA | I3: 94 min | J3: Stand-Up Comedy | K3: =IFERROR(VALUE(RIGHT(TRIM(F3),4)),"") -> 2016 | L3: =IF(TRIM(E3)="","Unknown",IFERROR(LEFT(TRIM(E3),FIND(",",TRIM(E3))-1),TRIM(E3))) -> United Kingdom | M3: =IFERROR(LEFT(J3,FIND(",",J3)-1),J3) -> Stand-Up Comedy | N3: =IF(B3="Movie",IFERROR(VALUE(LEFT(I3,FIND(" ",I3)-1)),""),"") -> 94 | O3: =IF(B3="TV Show",IFERROR(VALUE(LEFT(I3,FIND(" ",I3)-1)),""),"") | P3: =IF(K3="","",K3-G3) -> 0
A4: 70234439 | B4: TV Show | C4: Transformers Prime | E4: United States | F4: September 8, 2018 | G4: 2013 | H4: TV-Y7-FV | I4: 1 Season | J4: Kids' TV | K4: =IFERROR(VALUE(RIGHT(TRIM(F4),4)),"") -> 2018 | L4: =IF(TRIM(E4)="","Unknown",IFERROR(LEFT(TRIM(E4),FIND(",",TRIM(E4))-1),TRIM(E4))) -> United States | M4: =IFERROR(LEFT(J4,FIND(",",J4)-1),J4) -> Kids' TV | N4: =IF(B4="Movie",IFERROR(VALUE(LEFT(I4,FIND(" ",I4)-1)),""),"") | O4: =IF(B4="TV Show",IFERROR(VALUE(LEFT(I4,FIND(" ",I4)-1)),""),"") -> 1 | P4: =IF(K4="","",K4-G4) -> 5
A5: 80058654 | B5: TV Show | C5: Transformers: Robots in Disguise | E5: United States | F5: September 8, 2018 | G5: 2016 | H5: TV-Y7 | I5: 1 Season | J5: Kids' TV | K5: =IFERROR(VALUE(RIGHT(TRIM(F5),4)),"") -> 2018 | L5: =IF(TRIM(E5)="","Unknown",IFERROR(LEFT(TRIM(E5),FIND(",",TRIM(E5))-1),TRIM(E5))) -> United States | M5: =IFERROR(LEFT(J5,FIND(",",J5)-1),J5) -> Kids' TV | N5: =IF(B5="Movie",IFERROR(VALUE(LEFT(I5,FIND(" ",I5)-1)),""),"") | O5: =IF(B5="TV Show",IFERROR(VALUE(LEFT(I5,FIND(" ",I5)-1)),""),"") -> 1 | P5: =IF(K5="","",K5-G5) -> 2
A6: 80125979 | B6: Movie | C6: #realityhigh | D6: Fernando Lebrija | E6: United States | F6: September 8, 2017 | G6: 2017 | H6: TV-14 | I6: 99 min | J6: Comedies | K6: =IFERROR(VALUE(RIGHT(TRIM(F6),4)),"") -> 2017 | L6: =IF(TRIM(E6)="","Unknown",IFERROR(LEFT(TRIM(E6),FIND(",",TRIM(E6))-1),TRIM(E6))) -> United States | M6: =IFERROR(LEFT(J6,FIND(",",J6)-1),J6) -> Comedies | N6: =IF(B6="Movie",IFERROR(VALUE(LEFT(I6,FIND(" ",I6)-1)),""),"") -> 99 | O6: =IF(B6="TV Show",IFERROR(VALUE(LEFT(I6,FIND(" ",I6)-1)),""),"") | P6: =IF(K6="","",K6-G6) -> 0
A7: 80163890 | B7: TV Show | C7: Apaches | E7: Spain | F7: September 8, 2017 | G7: 2016 | H7: TV-MA | I7: 1 Season | J7: Crime TV Shows, International TV Shows, Spanish-Language TV Shows | K7: =IFERROR(VALUE(RIGHT(TRIM(F7),4)),"") -> 2017 | L7: =IF(TRIM(E7)="","Unknown",IFERROR(LEFT(TRIM(E7),FIND(",",TRIM(E7))-1),TRIM(E7))) -> Spain | M7: =IFERROR(LEFT(J7,FIND(",",J7)-1),J7) -> Crime TV Shows | N7: =IF(B7="Movie",IFERROR(VALUE(LEFT(I7,FIND(" ",I7)-1)),""),"") | O7: =IF(B7="TV Show",IFERROR(VALUE(LEFT(I7,FIND(" ",I7)-1)),""),"") -> 1 | P7: =IF(K7="","",K7-G7) -> 1
A8: 70304989 | B8: Movie | C8: Automata | D8: Gabe Ibáñez | E8: Bulgaria, United States, Spain, Canada | F8: September 8, 2017 | G8: 2014 | H8: R | I8: 110 min | J8: International Movies, Sci-Fi & Fantasy, Thrillers | K8: =IFERROR(VALUE(RIGHT(TRIM(F8),4)),"") -> 2017 | L8: =IF(TRIM(E8)="","Unknown",IFERROR(LEFT(TRIM(E8),FIND(",",TRIM(E8))-1),TRIM(E8))) -> Bulgaria | M8: =IFERROR(LEFT(J8,FIND(",",J8)-1),J8) -> International Movies | N8: =IF(B8="Movie",IFERROR(VALUE(LEFT(I8,FIND(" ",I8)-1)),""),"") -> 110 | O8: =IF(B8="TV Show",IFERROR(VALUE(LEFT(I8,FIND(" ",I8)-1)),""),"") | P8: =IF(K8="","",K8-G8) -> 3
A9: 80164077 | B9: Movie | C9: Fabrizio Copano: Solo pienso en mi | D9: Rodrigo Toro, Francisco Schultz | E9: Chile | F9: September 8, 2017 | G9: 2017 | H9: TV-MA | I9: 60 min | J9: Stand-Up Comedy | K9: =IFERROR(VALUE(RIGHT(TRIM(F9),4)),"") -> 2017 | L9: =IF(TRIM(E9)="","Unknown",IFERROR(LEFT(TRIM(E9),FIND(",",TRIM(E9))-1),TRIM(E9))) -> Chile | M9: =IFERROR(LEFT(J9,FIND(",",J9)-1),J9) -> Stand-Up Comedy | N9: =IF(B9="Movie",IFERROR(VALUE(LEFT(I9,FIND(" ",I9)-1)),""),"") -> 60 | O9: =IF(B9="TV Show",IFERROR(VALUE(LEFT(I9,FIND(" ",I9)-1)),""),"") | P9: =IF(K9="","",K9-G9) -> 0
A10: 80117902 | B10: TV Show | C10: Fire Chasers | E10: United States | F10: September 8, 2017 | G10: 2017 | H10: TV-MA | I10: 1 Season | J10: Docuseries, Science & Nature TV | K10: =IFERROR(VALUE(RIGHT(TRIM(F10),4)),"") -> 2017 | L10: =IF(TRIM(E10)="","Unknown",IFERROR(LEFT(TRIM(E10),FIND(",",TRIM(E10))-1),TRIM(E10))) -> United States | M10: =IFERROR(LEFT(J10,FIND(",",J10)-1),J10) -> Docuseries | N10: =IF(B10="Movie",IFERROR(VALUE(LEFT(I10,FIND(" ",I10)-1)),""),"") | O10: =IF(B10="TV Show",IFERROR(VALUE(LEFT(I10,FIND(" ",I10)-1)),""),"") -> 1 | P10: =IF(K10="","",K10-G10) -> 0
A11: 70304990 | B11: Movie | C11: Good People | D11: Henrik Ruben Genz | E11: United States, United Kingdom, Denmark, Sweden | F11: September 8, 2017 | G11: 2014 | H11: R | I11: 90 min | J11: Action & Adventure, Thrillers | K11: =IFERROR(VALUE(RIGHT(TRIM(F11),4)),"") -> 2017 | L11: =IF(TRIM(E11)="","Unknown",IFERROR(LEFT(TRIM(E11),FIND(",",TRIM(E11))-1),TRIM(E11))) -> United States | M11: =IFERROR(LEFT(J11,FIND(",",J11)-1),J11) -> Action & Adventure | N11: =IF(B11="Movie",IFERROR(VALUE(LEFT(I11,FIND(" ",I11)-1)),""),"") -> 90 | O11: =IF(B11="TV Show",IFERROR(VALUE(LEFT(I11,FIND(" ",I11)-1)),""),"") | P11: =IF(K11="","",K11-G11) -> 3
A12: 80169755 | B12: Movie | C12: Joaquín Reyes: Una y no más | D12: José Miguel Contreras | F12: September 8, 2017 | G12: 2017 | H12: TV-MA | I12: 78 min | J12: Stand-Up Comedy | K12: =IFERROR(VALUE(RIGHT(TRIM(F12),4)),"") -> 2017 | L12: =IF(TRIM(E12)="","Unknown",IFERROR(LEFT(TRIM(E12),FIND(",",TRIM(E12))-1),TRIM(E12))) -> Unknown | M12: =IFERROR(LEFT(J12,FIND(",",J12)-1),J12) -> Stand-Up Comedy | N12: =IF(B12="Movie",IFERROR(VALUE(LEFT(I12,FIND(" ",I12)-1)),""),"") -> 78 | O12: =IF(B12="TV Show",IFERROR(VALUE(LEFT(I12,FIND(" ",I12)-1)),""),"") | P12: =IF(K12="","",K12-G12) -> 0
A13: 70299204 | B13: Movie | C13: Kidnapping Mr. Heineken | D13: Daniel Alfredson | E13: Netherlands, Belgium, United Kingdom, United States | F13: September 8, 2017 | G13: 2015 | H13: R | I13: 95 min | J13: Action & Adventure, Dramas, International Movies | K13: =IFERROR(VALUE(RIGHT(TRIM(F13),4)),"") -> 2017 | L13: =IF(TRIM(E13)="","Unknown",IFERROR(LEFT(TRIM(E13),FIND(",",TRIM(E13))-1),TRIM(E13))) -> Netherlands | M13: =IFERROR(LEFT(J13,FIND(",",J13)-1),J13) -> Action & Adventure | N13: =IF(B13="Movie",IFERROR(VALUE(LEFT(I13,FIND(" ",I13)-1)),""),"") -> 95 | O13: =IF(B13="TV Show",IFERROR(VALUE(LEFT(I13,FIND(" ",I13)-1)),""),"") | P13: =IF(K13="","",K13-G13) -> 2
A14: 80182480 | B14: Movie | C14: Krish Trish and Baltiboy | F14: September 8, 2017 | G14: 2009 | H14: TV-Y7 | I14: 58 min | J14: Children & Family Movies | K14: =IFERROR(VALUE(RIGHT(TRIM(F14),4)),"") -> 2017 | L14: =IF(TRIM(E14)="","Unknown",IFERROR(LEFT(TRIM(E14),FIND(",",TRIM(E14))-1),TRIM(E14))) -> Unknown | M14: =IFERROR(LEFT(J14,FIND(",",J14)-1),J14) -> Children & Family Movies | N14: =IF(B14="Movie",IFERROR(VALUE(LEFT(I14,FIND(" ",I14)-1)),""),"") -> 58 | O14: =IF(B14="TV Show",IFERROR(VALUE(LEFT(I14,FIND(" ",I14)-1)),""),"") | P14: =IF(K14="","",K14-G14) -> 8
A15: 80182483 | B15: Movie | C15: Krish Trish and Baltiboy: Battle of Wits | D15: Munjal Shroff, Tilak Shetty | F15: September 8, 2017 | G15: 2013 | H15: TV-Y7 | I15: 62 min | J15: Children & Family Movies | K15: =IFERROR(VALUE(RIGHT(TRIM(F15),4)),"") -> 2017 | L15: =IF(TRIM(E15)="","Unknown",IFERROR(LEFT(TRIM(E15),FIND(",",TRIM(E15))-1),TRIM(E15))) -> Unknown | M15: =IFERROR(LEFT(J15,FIND(",",J15)-1),J15) -> Children & Family Movies | N15: =IF(B15="Movie",IFERROR(VALUE(LEFT(I15,FIND(" ",I15)-1)),""),"") -> 62 | O15: =IF(B15="TV Show",IFERROR(VALUE(LEFT(I15,FIND(" ",I15)-1)),""),"") | P15: =IF(K15="","",K15-G15) -> 4
A16: 80182596 | B16: Movie | C16: Krish Trish and Baltiboy: Best Friends Forever | D16: Munjal Shroff, Tilak Shetty | F16: September 8, 2017 | G16: 2016 | H16: TV-Y | I16: 65 min | J16: Children & Family Movies | K16: =IFERROR(VALUE(RIGHT(TRIM(F16),4)),"") -> 2017 | L16: =IF(TRIM(E16)="","Unknown",IFERROR(LEFT(TRIM(E16),FIND(",",TRIM(E16))-1),TRIM(E16))) -> Unknown | M16: =IFERROR(LEFT(J16,FIND(",",J16)-1),J16) -> Children & Family Movies | N16: =IF(B16="Movie",IFERROR(VALUE(LEFT(I16,FIND(" ",I16)-1)),""),"") -> 65 | O16: =IF(B16="TV Show",IFERROR(VALUE(LEFT(I16,FIND(" ",I16)-1)),""),"") | P16: =IF(K16="","",K16-G16) -> 1
A17: 80182482 | B17: Movie | C17: Krish Trish and Baltiboy: Comics of India | D17: Tilak Shetty | F17: September 8, 2017 | G17: 2012 | H17: TV-Y7 | I17: 61 min | J17: Children & Family Movies | K17: =IFERROR(VALUE(RIGHT(TRIM(F17),4)),"") -> 2017 | L17: =IF(TRIM(E17)="","Unknown",IFERROR(LEFT(TRIM(E17),FIND(",",TRIM(E17))-1),TRIM(E17))) -> Unknown | M17: =IFERROR(LEFT(J17,FIND(",",J17)-1),J17) -> Children & Family Movies | N17: =IF(B17="Movie",IFERROR(VALUE(LEFT(I17,FIND(" ",I17)-1)),""),"") -> 61 | O17: =IF(B17="TV Show",IFERROR(VALUE(LEFT(I17,FIND(" ",I17)-1)),""),"") | P17: =IF(K17="","",K17-G17) -> 5
A18: 80182597 | B18: Movie | C18: Krish Trish and Baltiboy: Oversmartness Never Pays | D18: Tilak Shetty | F18: September 8, 2017 | G18: 2017 | H18: TV-Y7 | I18: 65 min | J18: Children & Family Movies | K18: =IFERROR(VALUE(RIGHT(TRIM(F18),4)),"") -> 2017 | L18: =IF(TRIM(E18)="","Unknown",IFERROR(LEFT(TRIM(E18),FIND(",",TRIM(E18))-1),TRIM(E18))) -> Unknown | M18: =IFERROR(LEFT(J18,FIND(",",J18)-1),J18) -> Children & Family Movies | N18: =IF(B18="Movie",IFERROR(VALUE(LEFT(I18,FIND(" ",I18)-1)),""),"") -> 65 | O18: =IF(B18="TV Show",IFERROR(VALUE(LEFT(I18,FIND(" ",I18)-1)),""),"") | P18: =IF(K18="","",K18-G18) -> 0
A19: 80182481 | B19: Movie | C19: Krish Trish and Baltiboy: Part II | F19: September 8, 2017 | G19: 2010 | H19: TV-Y7 | I19: 58 min | J19: Children & Family Movies | K19: =IFERROR(VALUE(RIGHT(TRIM(F19),4)),"") -> 2017 | L19: =IF(TRIM(E19)="","Unknown",IFERROR(LEFT(TRIM(E19),FIND(",",TRIM(E19))-1),TRIM(E19))) -> Unknown | M19: =IFERROR(LEFT(J19,FIND(",",J19)-1),J19) -> Children & Family Movies | N19: =IF(B19="Movie",IFERROR(VALUE(LEFT(I19,FIND(" ",I19)-1)),""),"") -> 58 | O19: =IF(B19="TV Show",IFERROR(VALUE(LEFT(I19,FIND(" ",I19)-1)),""),"") | P19: =IF(K19="","",K19-G19) -> 7
A20: 80182621 | B20: Movie | C20: Krish Trish and Baltiboy: The Greatest Trick | D20: Munjal Shroff, Tilak Shetty | F20: September 8, 2017 | G20: 2013 | H20: TV-Y7 | I20: 60 min | J20: Children & Family Movies | K20: =IFERROR(VALUE(RIGHT(TRIM(F20),4)),"") -> 2017 | L20: =IF(TRIM(E20)="","Unknown",IFERROR(LEFT(TRIM(E20),FIND(",",TRIM(E20))-1),TRIM(E20))) -> Unknown | M20: =IFERROR(LEFT(J20,FIND(",",J20)-1),J20) -> Children & Family Movies | N20: =IF(B20="Movie",IFERROR(VALUE(LEFT(I20,FIND(" ",I20)-1)),""),"") -> 60 | O20: =IF(B20="TV Show",IFERROR(VALUE(LEFT(I20,FIND(" ",I20)-1)),""),"") | P20: =IF(K20="","",K20-G20) -> 4
A21: 80057969 | B21: Movie | C21: Love | D21: Gaspar Noé | E21: France, Belgium | F21: September 8, 2017 | G21: 2015 | H21: NR | I21: 135 min | J21: Cult Movies, Dramas, Independent Movies | K21: =IFERROR(VALUE(RIGHT(TRIM(F21),4)),"") -> 2017 | L21: =IF(TRIM(E21)="","Unknown",IFERROR(LEFT(TRIM(E21),FIND(",",TRIM(E21))-1),TRIM(E21))) -> France | M21: =IFERROR(LEFT(J21,FIND(",",J21)-1),J21) -> Cult Movies | N21: =IF(B21="Movie",IFERROR(VALUE(LEFT(I21,FIND(" ",I21)-1)),""),"") -> 135 | O21: =IF(B21="TV Show",IFERROR(VALUE(LEFT(I21,FIND(" ",I21)-1)),""),"") | P21: =IF(K21="","",K21-G21) -> 2
A22: 80060297 | B22: Movie | C22: Manhattan Romance | D22: Tom O'Brien | E22: United States | F22: September 8, 2017 | G22: 2014 | H22: TV-14 | I22: 98 min | J22: Comedies, Independent Movies, Romantic Movies | K22: =IFERROR(VALUE(RIGHT(TRIM(F22),4)),"") -> 2017 | L22: =IF(TRIM(E22)="","Unknown",IFERROR(LEFT(TRIM(E22),FIND(",",TRIM(E22))-1),TRIM(E22))) -> United States | M22: =IFERROR(LEFT(J22,FIND(",",J22)-1),J22) -> Comedies | N22: =IF(B22="Movie",IFERROR(VALUE(LEFT(I22,FIND(" ",I22)-1)),""),"") -> 98 | O22: =IF(B22="TV Show",IFERROR(VALUE(LEFT(I22,FIND(" ",I22)-1)),""),"") | P22: =IF(K22="","",K22-G22) -> 3
A23: 80046728 | B23: Movie | C23: Moonwalkers | D23: Antoine Bardou-Jacquet | E23: France, Belgium | F23: September 8, 2017 | G23: 2015 | H23: R | I23: 96 min | J23: Action & Adventure, Comedies, International Movies | K23: =IFERROR(VALUE(RIGHT(TRIM(F23),4)),"") -> 2017 | L23: =IF(TRIM(E23)="","Unknown",IFERROR(LEFT(TRIM(E23),FIND(",",TRIM(E23))-1),TRIM(E23))) -> France | M23: =IFERROR(LEFT(J23,FIND(",",J23)-1),J23) -> Action & Adventure | N23: =IF(B23="Movie",IFERROR(VALUE(LEFT(I23,FIND(" ",I23)-1)),""),"") -> 96 | O23: =IF(B23="TV Show",IFERROR(VALUE(LEFT(I23,FIND(" ",I23)-1)),""),"") | P23: =IF(K23="","",K23-G23) -> 2
A24: 80046727 | B24: Movie | C24: Rolling Papers | D24: Mitch Dickman | E24: United States, Uruguay | F24: September 8, 2017 | G24: 2015 | H24: TV-MA | I24: 79 min | J24: Documentaries | K24: =IFERROR(VALUE(RIGHT(TRIM(F24),4)),"") -> 2017 | L24: =IF(TRIM(E24)="","Unknown",IFERROR(LEFT(TRIM(E24),FIND(",",TRIM(E24))-1),TRIM(E24))) -> United States | M24: =IFERROR(LEFT(J24,FIND(",",J24)-1),J24) -> Documentaries | N24: =IF(B24="Movie",IFERROR(VALUE(LEFT(I24,FIND(" ",I24)-1)),""),"") -> 79 | O24: =IF(B24="TV Show",IFERROR(VALUE(LEFT(I24,FIND(" ",I24)-1)),""),"") | P24: =IF(K24="","",K24-G24) -> 2
A25: 70304988 | B25: Movie | C25: Stonehearst Asylum | D25: Brad Anderson | E25: United States | F25: September 8, 2017 | G25: 2014 | H25: PG-13 | I25: 113 min | J25: Horror Movies, Thrillers | K25: =IFERROR(VALUE(RIGHT(TRIM(F25),4)),"") -> 2017 | L25: =IF(TRIM(E25)="","Unknown",IFERROR(LEFT(TRIM(E25),FIND(",",TRIM(E25))-1),TRIM(E25))) -> United States | M25: =IFERROR(LEFT(J25,FIND(",",J25)-1),J25) -> Horror Movies | N25: =IF(B25="Movie",IFERROR(VALUE(LEFT(I25,FIND(" ",I25)-1)),""),"") -> 113 | O25: =IF(B25="TV Show",IFERROR(VALUE(LEFT(I25,FIND(" ",I25)-1)),""),"") | P25: =IF(K25="","",K25-G25) -> 3
A26: 80057700 | B26: Movie | C26: The Runner | D26: Austin Stark | E26: United States | F26: September 8, 2017 | G26: 2015 | H26: R | I26: 90 min | J26: Dramas, Independent Movies | K26: =IFERROR(VALUE(RIGHT(TRIM(F26),4)),"") -> 2017 | L26: =IF(TRIM(E26)="","Unknown",IFERROR(LEFT(TRIM(E26),FIND(",",TRIM(E26))-1),TRIM(E26))) -> United States | M26: =IFERROR(LEFT(J26,FIND(",",J26)-1),J26) -> Dramas | N26: =IF(B26="Movie",IFERROR(VALUE(LEFT(I26,FIND(" ",I26)-1)),""),"") -> 90 | O26: =IF(B26="TV Show",IFERROR(VALUE(LEFT(I26,FIND(" ",I26)-1)),""),"") | P26: =IF(K26="","",K26-G26) -> 2
A27: 80045922 | B27: Movie | C27: 6 Years | D27: Hannah Fidell | E27: United States | F27: September 8, 2015 | G27: 2015 | H27: NR | I27: 80 min | J27: Dramas, Independent Movies, Romantic Movies | K27: =IFERROR(VALUE(RIGHT(TRIM(F27),4)),"") -> 2015 | L27: =IF(TRIM(E27)="","Unknown",IFERROR(LEFT(TRIM(E27),FIND(",",TRIM(E27))-1),TRIM(E27))) -> United States | M27: =IFERROR(LEFT(J27,FIND(",",J27)-1),J27) -> Dramas | N27: =IF(B27="Movie",IFERROR(VALUE(LEFT(I27,FIND(" ",I27)-1)),""),"") -> 80 | O27: =IF(B27="TV Show",IFERROR(VALUE(LEFT(I27,FIND(" ",I27)-1)),""),"") | P27: =IF(K27="","",K27-G27) -> 0
A28: 80244601 | B28: TV Show | C28: Castle of Stars | F28: September 7, 2018 | G28: 2015 | H28: TV-14 | I28: 1 Season | J28: International TV Shows, Romantic TV Shows, TV Comedies | K28: =IFERROR(VALUE(RIGHT(TRIM(F28),4)),"") -> 2018 | L28: =IF(TRIM(E28)="","Unknown",IFERROR(LEFT(TRIM(E28),FIND(",",TRIM(E28))-1),TRIM(E28))) -> Unknown | M28: =IFERROR(LEFT(J28,FIND(",",J28)-1),J28) -> International TV Shows | N28: =IF(B28="Movie",IFERROR(VALUE(LEFT(I28,FIND(" ",I28)-1)),""),"") | O28: =IF(B28="TV Show",IFERROR(VALUE(LEFT(I28,FIND(" ",I28)-1)),""),"") -> 1 | P28: =IF(K28="","",K28-G28) -> 3
A29: 80203094 | B29: Movie | C29: City of Joy | D29: Madeleine Gavin | E29: United States, | F29: September 7, 2018 | G29: 2018 | H29: TV-MA | I29: 77 min | J29: Documentaries | K29: =IFERROR(VALUE(RIGHT(TRIM(F29),4)),"") -> 2018 | L29: =IF(TRIM(E29)="","Unknown",IFERROR(LEFT(TRIM(E29),FIND(",",TRIM(E29))-1),TRIM(E29))) -> United States | M29: =IFERROR(LEFT(J29,FIND(",",J29)-1),J29) -> Documentaries | N29: =IF(B29="Movie",IFERROR(VALUE(LEFT(I29,FIND(" ",I29)-1)),""),"") -> 77 | O29: =IF(B29="TV Show",IFERROR(VALUE(LEFT(I29,FIND(" ",I29)-1)),""),"") | P29: =IF(K29="","",K29-G29) -> 0
A30: 80190843 | B30: TV Show | C30: First and Last | F30: September 7, 2018 | G30: 2018 | H30: TV-MA | I30: 1 Season | J30: Docuseries | K30: =IFERROR(VALUE(RIGHT(TRIM(F30),4)),"") -> 2018 | L30: =IF(TRIM(E30)="","Unknown",IFERROR(LEFT(TRIM(E30),FIND(",",TRIM(E30))-1),TRIM(E30))) -> Unknown | M30: =IFERROR(LEFT(J30,FIND(",",J30)-1),J30) -> Docuseries | N30: =IF(B30="Movie",IFERROR(VALUE(LEFT(I30,FIND(" ",I30)-1)),""),"") | O30: =IF(B30="TV Show",IFERROR(VALUE(LEFT(I30,FIND(" ",I30)-1)),""),"") -> 1 | P30: =IF(K30="","",K30-G30) -> 0
A31: 70241607 | B31: Movie | C31: Laddaland | D31: Sopon Sukdapisit | E31: Thailand | F31: September 7, 2018 | G31: 2011 | H31: TV-MA | I31: 112 min | J31: Horror Movies, International Movies | K31: =IFERROR(VALUE(RIGHT(TRIM(F31),4)),"") -> 2018 | L31: =IF(TRIM(E31)="","Unknown",IFERROR(LEFT(TRIM(E31),FIND(",",TRIM(E31))-1),TRIM(E31))) -> Thailand | M31: =IFERROR(LEFT(J31,FIND(",",J31)-1),J31) -> Horror Movies | N31: =IF(B31="Movie",IFERROR(VALUE(LEFT(I31,FIND(" ",I31)-1)),""),"") -> 112 | O31: =IF(B31="TV Show",IFERROR(VALUE(LEFT(I31,FIND(" ",I31)-1)),""),"") | P31: =IF(K31="","",K31-G31) -> 7
A32: 80988892 | B32: Movie | C32: Next Gen | D32: Kevin R. Adams, Joe Ksander | E32: China, Canada, United States | F32: September 7, 2018 | G32: 2018 | H32: TV-PG | I32: 106 min | J32: Children & Family Movies, Comedies, Sci-Fi & Fantasy | K32: =IFERROR(VALUE(RIGHT(TRIM(F32),4)),"") -> 2018 | L32: =IF(TRIM(E32)="","Unknown",IFERROR(LEFT(TRIM(E32),FIND(",",TRIM(E32))-1),TRIM(E32))) -> China | M32: =IFERROR(LEFT(J32,FIND(",",J32)-1),J32) -> Children & Family Movies | N32: =IF(B32="Movie",IFERROR(VALUE(LEFT(I32,FIND(" ",I32)-1)),""),"") -> 106 | O32: =IF(B32="TV Show",IFERROR(VALUE(LEFT(I32,FIND(" ",I32)-1)),""),"") | P32: =IF(K32="","",K32-G32) -> 0
A33: 80239639 | B33: Movie | C33: Sierra Burgess Is A Loser | D33: Ian Samuels | E33: United States | F33: September 7, 2018 | G33: 2018 | H33: PG-13 | I33: 106 min | J33: Comedies, Romantic Movies | K33: =IFERROR(VALUE(RIGHT(TRIM(F33),4)),"") -> 2018 | L33: =IF(TRIM(E33)="","Unknown",IFERROR(LEFT(TRIM(E33),FIND(",",TRIM(E33))-1),TRIM(E33))) -> United States | M33: =IFERROR(LEFT(J33,FIND(",",J33)-1),J33) -> Comedies | N33: =IF(B33="Movie",IFERROR(VALUE(LEFT(I33,FIND(" ",I33)-1)),""),"") -> 106 | O33: =IF(B33="TV Show",IFERROR(VALUE(LEFT(I33,FIND(" ",I33)-1)),""),"") | P33: =IF(K33="","",K33-G33) -> 0
A34: 80159586 | B34: Movie | C34: The Most Assassinated Woman in the World | D34: Franck Ribière | E34: Belgium, United Kingdom, United States | F34: September 7, 2018 | G34: 2018 | H34: TV-MA | I34: 102 min | J34: Dramas, International Movies, Thrillers | K34: =IFERROR(VALUE(RIGHT(TRIM(F34),4)),"") -> 2018 | L34: =IF(TRIM(E34)="","Unknown",IFERROR(LEFT(TRIM(E34),FIND(",",TRIM(E34))-1),TRIM(E34))) -> Belgium | M34: =IFERROR(LEFT(J34,FIND(",",J34)-1),J34) -> Dramas | N34: =IF(B34="Movie",IFERROR(VALUE(LEFT(I34,FIND(" ",I34)-1)),""),"") -> 102 | O34: =IF(B34="TV Show",IFERROR(VALUE(LEFT(I34,FIND(" ",I34)-1)),""),"") | P34: =IF(K34="","",K34-G34) -> 0
A35: 80152447 | B35: Movie | C35: Cézanne et moi | D35: Daniele Thompson | E35: Belgium, France | F35: September 7, 2017 | G35: 2016 | H35: R | I35: 114 min | J35: Dramas, Independent Movies, International Movies | K35: =IFERROR(VALUE(RIGHT(TRIM(F35),4)),"") -> 2017 | L35: =IF(TRIM(E35)="","Unknown",IFERROR(LEFT(TRIM(E35),FIND(",",TRIM(E35))-1),TRIM(E35))) -> Belgium | M35: =IFERROR(LEFT(J35,FIND(",",J35)-1),J35) -> Dramas | N35: =IF(B35="Movie",IFERROR(VALUE(LEFT(I35,FIND(" ",I35)-1)),""),"") -> 114 | O35: =IF(B35="TV Show",IFERROR(VALUE(LEFT(I35,FIND(" ",I35)-1)),""),"") | P35: =IF(K35="","",K35-G35) -> 1
A36: 80221550 | B36: TV Show | C36: Archibald's Next Big Thing | F36: September 6, 2019 | G36: 2019 | H36: TV-Y7 | I36: 1 Season | J36: Kids' TV, TV Comedies | K36: =IFERROR(VALUE(RIGHT(TRIM(F36),4)),"") -> 2019 | L36: =IF(TRIM(E36)="","Unknown",IFERROR(LEFT(TRIM(E36),FIND(",",TRIM(E36))-1),TRIM(E36))) -> Unknown | M36: =IFERROR(LEFT(J36,FIND(",",J36)-1),J36) -> Kids' TV | N36: =IF(B36="Movie",IFERROR(VALUE(LEFT(I36,FIND(" ",I36)-1)),""),"") | O36: =IF(B36="TV Show",IFERROR(VALUE(LEFT(I36,FIND(" ",I36)-1)),""),"") -> 1 | P36: =IF(K36="","",K36-G36) -> 0
A37: 81154455 | B37: Movie | C37: Article 15 | D37: Anubhav Sinha | E37: India | F37: September 6, 2019 | G37: 2019 | H37: TV-MA | I37: 125 min | J37: Dramas, International Movies, Thrillers | K37: =IFERROR(VALUE(RIGHT(TRIM(F37),4)),"") -> 2019 | L37: =IF(TRIM(E37)="","Unknown",IFERROR(LEFT(TRIM(E37),FIND(",",TRIM(E37))-1),TRIM(E37))) -> India | M37: =IFERROR(LEFT(J37,FIND(",",J37)-1),J37) -> Dramas | N37: =IF(B37="Movie",IFERROR(VALUE(LEFT(I37,FIND(" ",I37)-1)),""),"") -> 125 | O37: =IF(B37="TV Show",IFERROR(VALUE(LEFT(I37,FIND(" ",I37)-1)),""),"") | P37: =IF(K37="","",K37-G37) -> 0
A38: 81113928 | B38: Movie | C38: Care of Kancharapalem | D38: Maha Venkatesh | F38: September 6, 2019 | G38: 2018 | H38: TV-14 | I38: 142 min | J38: Comedies, Dramas, Independent Movies | K38: =IFERROR(VALUE(RIGHT(TRIM(F38),4)),"") -> 2019 | L38: =IF(TRIM(E38)="","Unknown",IFERROR(LEFT(TRIM(E38),FIND(",",TRIM(E38))-1),TRIM(E38))) -> Unknown | M38: =IFERROR(LEFT(J38,FIND(",",J38)-1),J38) -> Comedies | N38: =IF(B38="Movie",IFERROR(VALUE(LEFT(I38,FIND(" ",I38)-1)),""),"") -> 142 | O38: =IF(B38="TV Show",IFERROR(VALUE(LEFT(I38,FIND(" ",I38)-1)),""),"") | P38: =IF(K38="","",K38-G38) -> 1
A39: 81052275 | B39: Movie | C39: Ee Nagaraniki Emaindi | D39: Tharun Bhascker | E39: India | F39: September 6, 2019 | G39: 2018 | H39: TV-14 | I39: 133 min | J39: Comedies, International Movies | K39: =IFERROR(VALUE(RIGHT(TRIM(F39),4)),"") -> 2019 | L39: =IF(TRIM(E39)="","Unknown",IFERROR(LEFT(TRIM(E39),FIND(",",TRIM(E39))-1),TRIM(E39))) -> India | M39: =IFERROR(LEFT(J39,FIND(",",J39)-1),J39) -> Comedies | N39: =IF(B39="Movie",IFERROR(VALUE(LEFT(I39,FIND(" ",I39)-1)),""),"") -> 133 | O39: =IF(B39="TV Show",IFERROR(VALUE(LEFT(I39,FIND(" ",I39)-1)),""),"") | P39: =IF(K39="","",K39-G39) -> 1
A40: 81132437 | B40: Movie | C40: Kill Me If You Dare | D40: Şenol Sönmez | F40: September 6, 2019 | G40: 2019 | H40: TV-14 | I40: 100 min | J40: Comedies, International Movies, Romantic Movies | K40: =IFERROR(VALUE(RIGHT(TRIM(F40),4)),"") -> 2019 | L40: =IF(TRIM(E40)="","Unknown",IFERROR(LEFT(TRIM(E40),FIND(",",TRIM(E40))-1),TRIM(E40))) -> Unknown | M40: =IFERROR(LEFT(J40,FIND(",",J40)-1),J40) -> Comedies | N40: =IF(B40="Movie",IFERROR(VALUE(LEFT(I40,FIND(" ",I40)-1)),""),"") -> 100 | O40: =IF(B40="TV Show",IFERROR(VALUE(LEFT(I40,FIND(" ",I40)-1)),""),"") | P40: =IF(K40="","",K40-G40) -> 0
A41: 80178151 | B41: TV Show | C41: The Spy | E41: France | F41: September 6, 2019 | G41: 2019 | H41: TV-MA | I41: 1 Season | J41: International TV Shows, TV Dramas, TV Thrillers | K41: =IFERROR(VALUE(RIGHT(TRIM(F41),4)),"") -> 2019 | L41: =IF(TRIM(E41)="","Unknown",IFERROR(LEFT(TRIM(E41),FIND(",",TRIM(E41))-1),TRIM(E41))) -> France | M41: =IFERROR(LEFT(J41,FIND(",",J41)-1),J41) -> International TV Shows | N41: =IF(B41="Movie",IFERROR(VALUE(LEFT(I41,FIND(" ",I41)-1)),""),"") | O41: =IF(B41="TV Show",IFERROR(VALUE(LEFT(I41,FIND(" ",I41)-1)),""),"") -> 1 | P41: =IF(K41="","",K41-G41) -> 0
A42: 80058026 | B42: Movie | C42: Hell and Back | D42: Tom Gianas, Ross R. Shuman | E42: United States | F42: September 6, 2018 | G42: 2015 | H42: R | I42: 86 min | J42: Action & Adventure, Comedies, Independent Movies | K42: =IFERROR(VALUE(RIGHT(TRIM(F42),4)),"") -> 2018 | L42: =IF(TRIM(E42)="","Unknown",IFERROR(LEFT(TRIM(E42),FIND(",",TRIM(E42))-1),TRIM(E42))) -> United States | M42: =IFERROR(LEFT(J42,FIND(",",J42)-1),J42) -> Action & Adventure | N42: =IF(B42="Movie",IFERROR(VALUE(LEFT(I42,FIND(" ",I42)-1)),""),"") -> 86 | O42: =IF(B42="TV Show",IFERROR(VALUE(LEFT(I42,FIND(" ",I42)-1)),""),"") | P42: =IF(K42="","",K42-G42) -> 3
A43: 70303496 | B43: Movie | C43: PK | D43: Rajkumar Hirani | E43: India | F43: September 6, 2018 | G43: 2014 | H43: TV-14 | I43: 146 min | J43: Comedies, Dramas, International Movies | K43: =IFERROR(VALUE(RIGHT(TRIM(F43),4)),"") -> 2018 | L43: =IF(TRIM(E43)="","Unknown",IFERROR(LEFT(TRIM(E43),FIND(",",TRIM(E43))-1),TRIM(E43))) -> India | M43: =IFERROR(LEFT(J43,FIND(",",J43)-1),J43) -> Comedies | N43: =IF(B43="Movie",IFERROR(VALUE(LEFT(I43,FIND(" ",I43)-1)),""),"") -> 146 | O43: =IF(B43="TV Show",IFERROR(VALUE(LEFT(I43,FIND(" ",I43)-1)),""),"") | P43: =IF(K43="","",K43-G43) -> 4
A44: 80162141 | B44: Movie | C44: Hard Tide | D44: Robert Osman, Nathanael Wiseman | E44: United Kingdom | F44: September 6, 2017 | G44: 2015 | H44: TV-MA | I44: 79 min | J44: Dramas, Independent Movies | K44: =IFERROR(VALUE(RIGHT(TRIM(F44),4)),"") -> 2017 | L44: =IF(TRIM(E44)="","Unknown",IFERROR(LEFT(TRIM(E44),FIND(",",TRIM(E44))-1),TRIM(E44))) -> United Kingdom | M44: =IFERROR(LEFT(J44,FIND(",",J44)-1),J44) -> Dramas | N44: =IF(B44="Movie",IFERROR(VALUE(LEFT(I44,FIND(" ",I44)-1)),""),"") -> 79 | O44: =IF(B44="TV Show",IFERROR(VALUE(LEFT(I44,FIND(" ",I44)-1)),""),"") | P44: =IF(K44="","",K44-G44) -> 2
A45: 80095641 | B45: Movie | C45: Elstree 1976 | D45: Jon Spira | E45: United Kingdom | F45: September 6, 2016 | G45: 2015 | H45: TV-PG | I45: 102 min | J45: Documentaries | K45: =IFERROR(VALUE(RIGHT(TRIM(F45),4)),"") -> 2016 | L45: =IF(TRIM(E45)="","Unknown",IFERROR(LEFT(TRIM(E45),FIND(",",TRIM(E45))-1),TRIM(E45))) -> United Kingdom | M45: =IFERROR(LEFT(J45,FIND(",",J45)-1),J45) -> Documentaries | N45: =IF(B45="Movie",IFERROR(VALUE(LEFT(I45,FIND(" ",I45)-1)),""),"") -> 102 | O45: =IF(B45="TV Show",IFERROR(VALUE(LEFT(I45,FIND(" ",I45)-1)),""),"") | P45: =IF(K45="","",K45-G45) -> 1
A46: 81176188 | B46: Movie | C46: American Factory: A Conversation with the Obamas | F46: September 5, 2019 | G46: 2019 | H46: TV-G | I46: 10 min | J46: Documentaries | K46: =IFERROR(VALUE(RIGHT(TRIM(F46),4)),"") -> 2019 | L46: =IF(TRIM(E46)="","Unknown",IFERROR(LEFT(TRIM(E46),FIND(",",TRIM(E46))-1),TRIM(E46))) -> Unknown | M46: =IFERROR(LEFT(J46,FIND(",",J46)-1),J46) -> Documentaries | N46: =IF(B46="Movie",IFERROR(VALUE(LEFT(I46,FIND(" ",I46)-1)),""),"") -> 10 | O46: =IF(B46="TV Show",IFERROR(VALUE(LEFT(I46,FIND(" ",I46)-1)),""),"") | P46: =IF(K46="","",K46-G46) -> 0
A47: 80159880 | B47: Movie | C47: ATM | D47: Mez Tharatorn | E47: United States, Canada | F47: September 5, 2018 | G47: 2012 | H47: TV-14 | I47: 122 min | J47: Comedies, International Movies, Romantic Movies | K47: =IFERROR(VALUE(RIGHT(TRIM(F47),4)),"") -> 2018 | L47: =IF(TRIM(E47)="","Unknown",IFERROR(LEFT(TRIM(E47),FIND(",",TRIM(E47))-1),TRIM(E47))) -> United States | M47: =IFERROR(LEFT(J47,FIND(",",J47)-1),J47) -> Comedies | N47: =IF(B47="Movie",IFERROR(VALUE(LEFT(I47,FIND(" ",I47)-1)),""),"") -> 122 | O47: =IF(B47="TV Show",IFERROR(VALUE(LEFT(I47,FIND(" ",I47)-1)),""),"") | P47: =IF(K47="","",K47-G47) -> 6
A48: 81016044 | B48: Movie | C48: Bangkok Traffic (Love) Story | D48: Adisorn Tresirikasem | E48: Thailand | F48: September 5, 2018 | G48: 2009 | H48: TV-14 | I48: 126 min | J48: Comedies, International Movies, Romantic Movies | K48: =IFERROR(VALUE(RIGHT(TRIM(F48),4)),"") -> 2018 | L48: =IF(TRIM(E48)="","Unknown",IFERROR(LEFT(TRIM(E48),FIND(",",TRIM(E48))-1),TRIM(E48))) -> Thailand | M48: =IFERROR(LEFT(J48,FIND(",",J48)-1),J48) -> Comedies | N48: =IF(B48="Movie",IFERROR(VALUE(LEFT(I48,FIND(" ",I48)-1)),""),"") -> 126 | O48: =IF(B48="TV Show",IFERROR(VALUE(LEFT(I48,FIND(" ",I48)-1)),""),"") | P48: =IF(K48="","",K48-G48) -> 9
A49: 80158838 | B49: Movie | C49: I Fine... Thank You... Love You | D49: Mez Tharatorn | E49: Thailand | F49: September 5, 2018 | G49: 2014 | H49: TV-14 | I49: 116 min | J49: Comedies, International Movies, Romantic Movies | K49: =IFERROR(VALUE(RIGHT(TRIM(F49),4)),"") -> 2018 | L49: =IF(TRIM(E49)="","Unknown",IFERROR(LEFT(TRIM(E49),FIND(",",TRIM(E49))-1),TRIM(E49))) -> Thailand | M49: =IFERROR(LEFT(J49,FIND(",",J49)-1),J49) -> Comedies | N49: =IF(B49="Movie",IFERROR(VALUE(LEFT(I49,FIND(" ",I49)-1)),""),"") -> 116 | O49: =IF(B49="TV Show",IFERROR(VALUE(LEFT(I49,FIND(" ",I49)-1)),""),"") | P49: =IF(K49="","",K49-G49) -> 4
A50: 81016045 | B50: Movie | C50: One Day | D50: Banjong Pisanthanakun | E50: Thailand | F50: September 5, 2018 | G50: 2016 | H50: TV-PG | I50: 135 min | J50: Dramas, International Movies, Romantic Movies | K50: =IFERROR(VALUE(RIGHT(TRIM(F50),4)),"") -> 2018 | L50: =IF(TRIM(E50)="","Unknown",IFERROR(LEFT(TRIM(E50),FIND(",",TRIM(E50))-1),TRIM(E50))) -> Thailand | M50: =IFERROR(LEFT(J50,FIND(",",J50)-1),J50) -> Dramas | N50: =IF(B50="Movie",IFERROR(VALUE(LEFT(I50,FIND(" ",I50)-1)),""),"") -> 135 | O50: =IF(B50="TV Show",IFERROR(VALUE(LEFT(I50,FIND(" ",I50)-1)),""),"") | P50: =IF(K50="","",K50-G50) -> 2
A51: 70142798 | B51: Movie | C51: Phobia 2 | D51: Banjong Pisanthanakun, Paween Purikitpanya, Songyos Sugmakanan, Parkpoom Wongpoom, Visute Poolvoralaks | E51: Thailand | F51: September 5, 2018 | G51: 2009 | H51: TV-MA | I51: 125 min | J51: Horror Movies, International Movies | K51: =IFERROR(VALUE(RIGHT(TRIM(F51),4)),"") -> 2018 | L51: =IF(TRIM(E51)="","Unknown",IFERROR(LEFT(TRIM(E51),FIND(",",TRIM(E51))-1),TRIM(E51))) -> Thailand | M51: =IFERROR(LEFT(J51,FIND(",",J51)-1),J51) -> Horror Movies | N51: =IF(B51="Movie",IFERROR(VALUE(LEFT(I51,FIND(" ",I51)-1)),""),"") -> 125 | O51: =IF(B51="TV Show",IFERROR(VALUE(LEFT(I51,FIND(" ",I51)-1)),""),"") | P51: =IF(K51="","",K51-G51) -> 9
A52: 70062814 | B52: Movie | C52: Shutter | D52: Banjong Pisanthanakun, Parkpoom Wongpoom | E52: Thailand | F52: September 5, 2018 | G52: 2004 | H52: TV-MA | I52: 96 min | J52: Horror Movies, International Movies | K52: =IFERROR(VALUE(RIGHT(TRIM(F52),4)),"") -> 2018 | L52: =IF(TRIM(E52)="","Unknown",IFERROR(LEFT(TRIM(E52),FIND(",",TRIM(E52))-1),TRIM(E52))) -> Thailand | M52: =IFERROR(LEFT(J52,FIND(",",J52)-1),J52) -> Horror Movies | N52: =IF(B52="Movie",IFERROR(VALUE(LEFT(I52,FIND(" ",I52)-1)),""),"") -> 96 | O52: =IF(B52="TV Show",IFERROR(VALUE(LEFT(I52,FIND(" ",I52)-1)),""),"") | P52: =IF(K52="","",K52-G52) -> 14
A53: 80158839 | B53: Movie | C53: Suckseed | D53: Chayanop Boonprakob | E53: Thailand | F53: September 5, 2018 | G53: 2011 | H53: TV-MA | I53: 130 min | J53: Comedies, International Movies | K53: =IFERROR(VALUE(RIGHT(TRIM(F53),4)),"") -> 2018 | L53: =IF(TRIM(E53)="","Unknown",IFERROR(LEFT(TRIM(E53),FIND(",",TRIM(E53))-1),TRIM(E53))) -> Thailand | M53: =IFERROR(LEFT(J53,FIND(",",J53)-1),J53) -> Comedies | N53: =IF(B53="Movie",IFERROR(VALUE(LEFT(I53,FIND(" ",I53)-1)),""),"") -> 130 | O53: =IF(B53="TV Show",IFERROR(VALUE(LEFT(I53,FIND(" ",I53)-1)),""),"") | P53: =IF(K53="","",K53-G53) -> 7
A54: 80147760 | B54: Movie | C54: Carrie Pilby | D54: Susan Johnson | E54: United States | F54: September 5, 2017 | G54: 2016 | H54: TV-14 | I54: 98 min | J54: Comedies, Dramas | K54: =IFERROR(VALUE(RIGHT(TRIM(F54),4)),"") -> 2017 | L54: =IF(TRIM(E54)="","Unknown",IFERROR(LEFT(TRIM(E54),FIND(",",TRIM(E54))-1),TRIM(E54))) -> United States | M54: =IFERROR(LEFT(J54,FIND(",",J54)-1),J54) -> Comedies | N54: =IF(B54="Movie",IFERROR(VALUE(LEFT(I54,FIND(" ",I54)-1)),""),"") -> 98 | O54: =IF(B54="TV Show",IFERROR(VALUE(LEFT(I54,FIND(" ",I54)-1)),""),"") | P54: =IF(K54="","",K54-G54) -> 1
A55: 80177405 | B55: Movie | C55: Marc Maron: Too Real | D55: Lynn Shelton | E55: United States | F55: September 5, 2017 | G55: 2017 | H55: TV-MA | I55: 70 min | J55: Stand-Up Comedy | K55: =IFERROR(VALUE(RIGHT(TRIM(F55),4)),"") -> 2017 | L55: =IF(TRIM(E55)="","Unknown",IFERROR(LEFT(TRIM(E55),FIND(",",TRIM(E55))-1),TRIM(E55))) -> United States | M55: =IFERROR(LEFT(J55,FIND(",",J55)-1),J55) -> Stand-Up Comedy | N55: =IF(B55="Movie",IFERROR(VALUE(LEFT(I55,FIND(" ",I55)-1)),""),"") -> 70 | O55: =IF(B55="TV Show",IFERROR(VALUE(LEFT(I55,FIND(" ",I55)-1)),""),"") | P55: =IF(K55="","",K55-G55) -> 0
A56: 80113482 | B56: TV Show | C56: No Tomorrow | E56: United States | F56: September 5, 2017 | G56: 2016 | H56: TV-14 | I56: 1 Season | J56: Romantic TV Shows, TV Comedies, TV Dramas | K56: =IFERROR(VALUE(RIGHT(TRIM(F56),4)),"") -> 2017 | L56: =IF(TRIM(E56)="","Unknown",IFERROR(LEFT(TRIM(E56),FIND(",",TRIM(E56))-1),TRIM(E56))) -> United States | M56: =IFERROR(LEFT(J56,FIND(",",J56)-1),J56) -> Romantic TV Shows | N56: =IF(B56="Movie",IFERROR(VALUE(LEFT(I56,FIND(" ",I56)-1)),""),"") | O56: =IF(B56="TV Show",IFERROR(VALUE(LEFT(I56,FIND(" ",I56)-1)),""),"") -> 1 | P56: =IF(K56="","",K56-G56) -> 1
A57: 81160036 | B57: Movie | C57: Saawan | D57: Farhan Alam | E57: Pakistan | F57: September 4, 2019 | G57: 2016 | H57: TV-14 | I57: 128 min | J57: Dramas, Independent Movies, International Movies | K57: =IFERROR(VALUE(RIGHT(TRIM(F57),4)),"") -> 2019 | L57: =IF(TRIM(E57)="","Unknown",IFERROR(LEFT(TRIM(E57),FIND(",",TRIM(E57))-1),TRIM(E57))) -> Pakistan | M57: =IFERROR(LEFT(J57,FIND(",",J57)-1),J57) -> Dramas | N57: =IF(B57="Movie",IFERROR(VALUE(LEFT(I57,FIND(" ",I57)-1)),""),"") -> 128 | O57: =IF(B57="TV Show",IFERROR(VALUE(LEFT(I57,FIND(" ",I57)-1)),""),"") | P57: =IF(K57="","",K57-G57) -> 3
A58: 81173255 | B58: Movie | C58: The Heretics | D58: Chad Archibald | E58: Canada | F58: September 4, 2019 | G58: 2017 | H58: TV-MA | I58: 88 min | J58: Horror Movies | K58: =IFERROR(VALUE(RIGHT(TRIM(F58),4)),"") -> 2019 | L58: =IF(TRIM(E58)="","Unknown",IFERROR(LEFT(TRIM(E58),FIND(",",TRIM(E58))-1),TRIM(E58))) -> Canada | M58: =IFERROR(LEFT(J58,FIND(",",J58)-1),J58) -> Horror Movies | N58: =IF(B58="Movie",IFERROR(VALUE(LEFT(I58,FIND(" ",I58)-1)),""),"") -> 88 | O58: =IF(B58="TV Show",IFERROR(VALUE(LEFT(I58,FIND(" ",I58)-1)),""),"") | P58: =IF(K58="","",K58-G58) -> 2
A59: 81078908 | B59: Movie | C59: The World We Make | D59: Brian Baugh | E59: United States | F59: September 4, 2019 | G59: 2019 | H59: PG | I59: 108 min | J59: Dramas, Romantic Movies | K59: =IFERROR(VALUE(RIGHT(TRIM(F59),4)),"") -> 2019 | L59: =IF(TRIM(E59)="","Unknown",IFERROR(LEFT(TRIM(E59),FIND(",",TRIM(E59))-1),TRIM(E59))) -> United States | M59: =IFERROR(LEFT(J59,FIND(",",J59)-1),J59) -> Dramas | N59: =IF(B59="Movie",IFERROR(VALUE(LEFT(I59,FIND(" ",I59)-1)),""),"") -> 108 | O59: =IF(B59="TV Show",IFERROR(VALUE(LEFT(I59,FIND(" ",I59)-1)),""),"") | P59: =IF(K59="","",K59-G59) -> 0
A60: 81155784 | B60: Movie | C60: Watchman | D60: A. L. Vijay | E60: India | F60: September 4, 2019 | G60: 2019 | H60: TV-14 | I60: 93 min | J60: Comedies, Dramas, International Movies | K60: =IFERROR(VALUE(RIGHT(TRIM(F60),4)),"") -> 2019 | L60: =IF(TRIM(E60)="","Unknown",IFERROR(LEFT(TRIM(E60),FIND(",",TRIM(E60))-1),TRIM(E60))) -> India | M60: =IFERROR(LEFT(J60,FIND(",",J60)-1),J60) -> Comedies | N60: =IF(B60="Movie",IFERROR(VALUE(LEFT(I60,FIND(" ",I60)-1)),""),"") -> 93 | O60: =IF(B60="TV Show",IFERROR(VALUE(LEFT(I60,FIND(" ",I60)-1)),""),"") | P60: =IF(K60="","",K60-G60) -> 0
A61: 80201906 | B61: Movie | C61: Black Panther | D61: Ryan Coogler | E61: United States | F61: September 4, 2018 | G61: 2018 | H61: PG-13 | I61: 135 min | J61: Action & Adventure, Sci-Fi & Fantasy | K61: =IFERROR(VALUE(RIGHT(TRIM(F61),4)),"") -> 2018 | L61: =IF(TRIM(E61)="","Unknown",IFERROR(LEFT(TRIM(E61),FIND(",",TRIM(E61))-1),TRIM(E61))) -> United States | M61: =IFERROR(LEFT(J61,FIND(",",J61)-1),J61) -> Action & Adventure | N61: =IF(B61="Movie",IFERROR(VALUE(LEFT(I61,FIND(" ",I61)-1)),""),"") -> 135 | O61: =IF(B61="TV Show",IFERROR(VALUE(LEFT(I61,FIND(" ",I61)-1)),""),"") | P61: =IF(K61="","",K61-G61) -> 0
A62: 80052612 | B62: Movie | C62: Man Up | D62: Ben Palmer | E62: United Kingdom, France | F62: September 4, 2018 | G62: 2015 | H62: R | I62: 88 min | J62: Comedies, International Movies, Romantic Movies | K62: =IFERROR(VALUE(RIGHT(TRIM(F62),4)),"") -> 2018 | L62: =IF(TRIM(E62)="","Unknown",IFERROR(LEFT(TRIM(E62),FIND(",",TRIM(E62))-1),TRIM(E62))) -> United Kingdom | M62: =IFERROR(LEFT(J62,FIND(",",J62)-1),J62) -> Comedies | N62: =IF(B62="Movie",IFERROR(VALUE(LEFT(I62,FIND(" ",I62)-1)),""),"") -> 88 | O62: =IF(B62="TV Show",IFERROR(VALUE(LEFT(I62,FIND(" ",I62)-1)),""),"") | P62: =IF(K62="","",K62-G62) -> 3
A63: 80113641 | B63: TV Show | C63: Frequency | E63: United States | F63: September 4, 2017 | G63: 2016 | H63: TV-14 | I63: 1 Season | J63: Crime TV Shows, TV Dramas, TV Mysteries | K63: =IFERROR(VALUE(RIGHT(TRIM(F63),4)),"") -> 2017 | L63: =IF(TRIM(E63)="","Unknown",IFERROR(LEFT(TRIM(E63),FIND(",",TRIM(E63))-1),TRIM(E63))) -> United States | M63: =IFERROR(LEFT(J63,FIND(",",J63)-1),J63) -> Crime TV Shows | N63: =IF(B63="Movie",IFERROR(VALUE(LEFT(I63,FIND(" ",I63)-1)),""),"") | O63: =IF(B63="TV Show",IFERROR(VALUE(LEFT(I63,FIND(" ",I63)-1)),""),"") -> 1 | P63: =IF(K63="","",K63-G63) -> 1
A64: 81054495 | B64: Movie | C64: Mo Gilligan: Momentum | D64: Chris Howe | E64: United Kingdom | F64: September 30, 2019 | G64: 2019 | H64: TV-MA | I64: 64 min | J64: Stand-Up Comedy | K64: =IFERROR(VALUE(RIGHT(TRIM(F64),4)),"") -> 2019 | L64: =IF(TRIM(E64)="","Unknown",IFERROR(LEFT(TRIM(E64),FIND(",",TRIM(E64))-1),TRIM(E64))) -> United Kingdom | M64: =IFERROR(LEFT(J64,FIND(",",J64)-1),J64) -> Stand-Up Comedy | N64: =IF(B64="Movie",IFERROR(VALUE(LEFT(I64,FIND(" ",I64)-1)),""),"") -> 64 | O64: =IF(B64="TV Show",IFERROR(VALUE(LEFT(I64,FIND(" ",I64)-1)),""),"") | P64: =IF(K64="","",K64-G64) -> 0
A65: 80996949 | B65: TV Show | C65: Adam Ruins Everything | E65: United States | F65: September 30, 2018 | G65: 2018 | H65: TV-14 | I65: 1 Season | J65: TV Comedies | K65: =IFERROR(VALUE(RIGHT(TRIM(F65),4)),"") -> 2018 | L65: =IF(TRIM(E65)="","Unknown",IFERROR(LEFT(TRIM(E65),FIND(",",TRIM(E65))-1),TRIM(E65))) -> United States | M65: =IFERROR(LEFT(J65,FIND(",",J65)-1),J65) -> TV Comedies | N65: =IF(B65="Movie",IFERROR(VALUE(LEFT(I65,FIND(" ",I65)-1)),""),"") | O65: =IF(B65="TV Show",IFERROR(VALUE(LEFT(I65,FIND(" ",I65)-1)),""),"") -> 1 | P65: =IF(K65="","",K65-G65) -> 0
A66: 80239337 | B66: TV Show | C66: Ben 10 | E66: United States | F66: September 30, 2018 | G66: 2016 | H66: TV-Y7 | I66: 1 Season | J66: Kids' TV | K66: =IFERROR(VALUE(RIGHT(TRIM(F66),4)),"") -> 2018 | L66: =IF(TRIM(E66)="","Unknown",IFERROR(LEFT(TRIM(E66),FIND(",",TRIM(E66))-1),TRIM(E66))) -> United States | M66: =IFERROR(LEFT(J66,FIND(",",J66)-1),J66) -> Kids' TV | N66: =IF(B66="Movie",IFERROR(VALUE(LEFT(I66,FIND(" ",I66)-1)),""),"") | O66: =IF(B66="TV Show",IFERROR(VALUE(LEFT(I66,FIND(" ",I66)-1)),""),"") -> 1 | P66: =IF(K66="","",K66-G66) -> 2
A67: 70212504 | B67: Movie | C67: Big Miracle | D67: Ken Kwapis | E67: United States, United Kingdom | F67: September 30, 2018 | G67: 2012 | H67: PG | I67: 107 min | J67: Children & Family Movies, Dramas | K67: =IFERROR(VALUE(RIGHT(TRIM(F67),4)),"") -> 2018 | L67: =IF(TRIM(E67)="","Unknown",IFERROR(LEFT(TRIM(E67),FIND(",",TRIM(E67))-1),TRIM(E67))) -> United States | M67: =IFERROR(LEFT(J67,FIND(",",J67)-1),J67) -> Children & Family Movies | N67: =IF(B67="Movie",IFERROR(VALUE(LEFT(I67,FIND(" ",I67)-1)),""),"") -> 107 | O67: =IF(B67="TV Show",IFERROR(VALUE(LEFT(I67,FIND(" ",I67)-1)),""),"") | P67: =IF(K67="","",K67-G67) -> 6
A68: 81011682 | B68: TV Show | C68: Christiane Amanpour: Sex & Love Around the World | E68: United States | F68: September 30, 2018 | G68: 2018 | H68: TV-MA | I68: 1 Season | J68: Docuseries | K68: =IFERROR(VALUE(RIGHT(TRIM(F68),4)),"") -> 2018 | L68: =IF(TRIM(E68)="","Unknown",IFERROR(LEFT(TRIM(E68),FIND(",",TRIM(E68))-1),TRIM(E68))) -> United States | M68: =IFERROR(LEFT(J68,FIND(",",J68)-1),J68) -> Docuseries | N68: =IF(B68="Movie",IFERROR(VALUE(LEFT(I68,FIND(" ",I68)-1)),""),"") | O68: =IF(B68="TV Show",IFERROR(VALUE(LEFT(I68,FIND(" ",I68)-1)),""),"") -> 1 | P68: =IF(K68="","",K68-G68) -> 0
A69: 80128317 | B69: TV Show | C69: The Eighties | E69: United States | F69: September 30, 2018 | G69: 2016 | H69: TV-PG | I69: 1 Season | J69: Docuseries | K69: =IFERROR(VALUE(RIGHT(TRIM(F69),4)),"") -> 2018 | L69: =IF(TRIM(E69)="","Unknown",IFERROR(LEFT(TRIM(E69),FIND(",",TRIM(E69))-1),TRIM(E69))) -> United States | M69: =IFERROR(LEFT(J69,FIND(",",J69)-1),J69) -> Docuseries | N69: =IF(B69="Movie",IFERROR(VALUE(LEFT(I69,FIND(" ",I69)-1)),""),"") | O69: =IF(B69="TV Show",IFERROR(VALUE(LEFT(I69,FIND(" ",I69)-1)),""),"") -> 1 | P69: =IF(K69="","",K69-G69) -> 2
A70: 81027384 | B70: TV Show | C70: The Nineties | E70: United States | F70: September 30, 2018 | G70: 2017 | H70: TV-14 | I70: 1 Season | J70: Docuseries | K70: =IFERROR(VALUE(RIGHT(TRIM(F70),4)),"") -> 2018 | L70: =IF(TRIM(E70)="","Unknown",IFERROR(LEFT(TRIM(E70),FIND(",",TRIM(E70))-1),TRIM(E70))) -> United States | M70: =IFERROR(LEFT(J70,FIND(",",J70)-1),J70) -> Docuseries | N70: =IF(B70="Movie",IFERROR(VALUE(LEFT(I70,FIND(" ",I70)-1)),""),"") | O70: =IF(B70="TV Show",IFERROR(VALUE(LEFT(I70,FIND(" ",I70)-1)),""),"") -> 1 | P70: =IF(K70="","",K70-G70) -> 1
A71: 80030186 | B71: TV Show | C71: The Seventies | E71: United States | F71: September 30, 2018 | G71: 2015 | H71: TV-PG | I71: 1 Season | J71: Docuseries | K71: =IFERROR(VALUE(RIGHT(TRIM(F71),4)),"") -> 2018 | L71: =IF(TRIM(E71)="","Unknown",IFERROR(LEFT(TRIM(E71),FIND(",",TRIM(E71))-1),TRIM(E71))) -> United States | M71: =IFERROR(LEFT(J71,FIND(",",J71)-1),J71) -> Docuseries | N71: =IF(B71="Movie",IFERROR(VALUE(LEFT(I71,FIND(" ",I71)-1)),""),"") | O71: =IF(B71="TV Show",IFERROR(VALUE(LEFT(I71,FIND(" ",I71)-1)),""),"") -> 1 | P71: =IF(K71="","",K71-G71) -> 3
A72: 80116921 | B72: TV Show | C72: We Bare Bears | E72: United States | F72: September 30, 2018 | G72: 2017 | H72: TV-Y7 | I72: 1 Season | J72: Kids' TV, TV Comedies | K72: =IFERROR(VALUE(RIGHT(TRIM(F72),4)),"") -> 2018 | L72: =IF(TRIM(E72)="","Unknown",IFERROR(LEFT(TRIM(E72),FIND(",",TRIM(E72))-1),TRIM(E72))) -> United States | M72: =IFERROR(LEFT(J72,FIND(",",J72)-1),J72) -> Kids' TV | N72: =IF(B72="Movie",IFERROR(VALUE(LEFT(I72,FIND(" ",I72)-1)),""),"") | O72: =IF(B72="TV Show",IFERROR(VALUE(LEFT(I72,FIND(" ",I72)-1)),""),"") -> 1 | P72: =IF(K72="","",K72-G72) -> 1
A73: 80187061 | B73: Movie | C73: The Mayor | D73: Park In-je | E73: South Korea | F73: September 30, 2017 | G73: 2017 | H73: TV-MA | I73: 130 min | J73: Dramas, International Movies | K73: =IFERROR(VALUE(RIGHT(TRIM(F73),4)),"") -> 2017 | L73: =IF(TRIM(E73)="","Unknown",IFERROR(LEFT(TRIM(E73),FIND(",",TRIM(E73))-1),TRIM(E73))) -> South Korea | M73: =IFERROR(LEFT(J73,FIND(",",J73)-1),J73) -> Dramas | N73: =IF(B73="Movie",IFERROR(VALUE(LEFT(I73,FIND(" ",I73)-1)),""),"") -> 130 | O73: =IF(B73="TV Show",IFERROR(VALUE(LEFT(I73,FIND(" ",I73)-1)),""),"") | P73: =IF(K73="","",K73-G73) -> 0
A74: 80181555 | B74: TV Show | C74: The Royal House of Windsor | E74: United Kingdom | F74: September 30, 2017 | G74: 2017 | H74: TV-14 | I74: 1 Season | J74: British TV Shows, Docuseries, International TV Shows | K74: =IFERROR(VALUE(RIGHT(TRIM(F74),4)),"") -> 2017 | L74: =IF(TRIM(E74)="","Unknown",IFERROR(LEFT(TRIM(E74),FIND(",",TRIM(E74))-1),TRIM(E74))) -> United Kingdom | M74: =IFERROR(LEFT(J74,FIND(",",J74)-1),J74) -> British TV Shows | N74: =IF(B74="Movie",IFERROR(VALUE(LEFT(I74,FIND(" ",I74)-1)),""),"") | O74: =IF(B74="TV Show",IFERROR(VALUE(LEFT(I74,FIND(" ",I74)-1)),""),"") -> 1 | P74: =IF(K74="","",K74-G74) -> 0
A75: 80081155 | B75: Movie | C75: Amanda Knox | D75: Rod Blackhurst, Brian McGinn | E75: Denmark, United States | F75: September 30, 2016 | G75: 2016 | H75: TV-MA | I75: 92 min | J75: Documentaries | K75: =IFERROR(VALUE(RIGHT(TRIM(F75),4)),"") -> 2016 | L75: =IF(TRIM(E75)="","Unknown",IFERROR(LEFT(TRIM(E75),FIND(",",TRIM(E75))-1),TRIM(E75))) -> Denmark | M75: =IFERROR(LEFT(J75,FIND(",",J75)-1),J75) -> Documentaries | N75: =IF(B75="Movie",IFERROR(VALUE(LEFT(I75,FIND(" ",I75)-1)),""),"") -> 92 | O75: =IF(B75="TV Show",IFERROR(VALUE(LEFT(I75,FIND(" ",I75)-1)),""),"") | P75: =IF(K75="","",K75-G75) -> 0
A76: 80184358 | B76: TV Show | C76: Lovesick | F76: September 3, 2018 | G76: 2014 | H76: TV-14 | I76: 1 Season | J76: International TV Shows, Romantic TV Shows, TV Dramas | K76: =IFERROR(VALUE(RIGHT(TRIM(F76),4)),"") -> 2018 | L76: =IF(TRIM(E76)="","Unknown",IFERROR(LEFT(TRIM(E76),FIND(",",TRIM(E76))-1),TRIM(E76))) -> Unknown | M76: =IFERROR(LEFT(J76,FIND(",",J76)-1),J76) -> International TV Shows | N76: =IF(B76="Movie",IFERROR(VALUE(LEFT(I76,FIND(" ",I76)-1)),""),"") | O76: =IF(B76="TV Show",IFERROR(VALUE(LEFT(I76,FIND(" ",I76)-1)),""),"") -> 1 | P76: =IF(K76="","",K76-G76) -> 4
A77: 80198585 | B77: Movie | C77: The Debt Collector | D77: Jesse V. Johnson | E77: United Kingdom, United States | F77: September 3, 2018 | G77: 2018 | H77: TV-MA | I77: 96 min | J77: Action & Adventure | K77: =IFERROR(VALUE(RIGHT(TRIM(F77),4)),"") -> 2018 | L77: =IF(TRIM(E77)="","Unknown",IFERROR(LEFT(TRIM(E77),FIND(",",TRIM(E77))-1),TRIM(E77))) -> United Kingdom | M77: =IFERROR(LEFT(J77,FIND(",",J77)-1),J77) -> Action & Adventure | N77: =IF(B77="Movie",IFERROR(VALUE(LEFT(I77,FIND(" ",I77)-1)),""),"") -> 96 | O77: =IF(B77="TV Show",IFERROR(VALUE(LEFT(I77,FIND(" ",I77)-1)),""),"") | P77: =IF(K77="","",K77-G77) -> 0
A78: 70233894 | B78: Movie | C78: Act of Vengeance | D78: Mahsun Kırmızıgül | E78: Turkey, United States | F78: September 29, 2018 | G78: 2010 | H78: NR | I78: 112 min | J78: Action & Adventure, International Movies | K78: =IFERROR(VALUE(RIGHT(TRIM(F78),4)),"") -> 2018 | L78: =IF(TRIM(E78)="","Unknown",IFERROR(LEFT(TRIM(E78),FIND(",",TRIM(E78))-1),TRIM(E78))) -> Turkey | M78: =IFERROR(LEFT(J78,FIND(",",J78)-1),J78) -> Action & Adventure | N78: =IF(B78="Movie",IFERROR(VALUE(LEFT(I78,FIND(" ",I78)-1)),""),"") -> 112 | O78: =IF(B78="TV Show",IFERROR(VALUE(LEFT(I78,FIND(" ",I78)-1)),""),"") | P78: =IF(K78="","",K78-G78) -> 8
A79: 81011955 | B79: Movie | C79: Paradise Lost | D79: Monique Gardenberg | E79: Brazil | F79: September 29, 2018 | G79: 2018 | H79: TV-MA | I79: 111 min | J79: Dramas, Independent Movies, International Movies | K79: =IFERROR(VALUE(RIGHT(TRIM(F79),4)),"") -> 2018 | L79: =IF(TRIM(E79)="","Unknown",IFERROR(LEFT(TRIM(E79),FIND(",",TRIM(E79))-1),TRIM(E79))) -> Brazil | M79: =IFERROR(LEFT(J79,FIND(",",J79)-1),J79) -> Dramas | N79: =IF(B79="Movie",IFERROR(VALUE(LEFT(I79,FIND(" ",I79)-1)),""),"") -> 111 | O79: =IF(B79="TV Show",IFERROR(VALUE(LEFT(I79,FIND(" ",I79)-1)),""),"") | P79: =IF(K79="","",K79-G79) -> 0
A80: 80128722 | B80: Movie | C80: Gerald's Game | D80: Mike Flanagan | E80: United States | F80: September 29, 2017 | G80: 2017 | H80: TV-MA | I80: 103 min | J80: Horror Movies, Thrillers | K80: =IFERROR(VALUE(RIGHT(TRIM(F80),4)),"") -> 2017 | L80: =IF(TRIM(E80)="","Unknown",IFERROR(LEFT(TRIM(E80),FIND(",",TRIM(E80))-1),TRIM(E80))) -> United States | M80: =IFERROR(LEFT(J80,FIND(",",J80)-1),J80) -> Horror Movies | N80: =IF(B80="Movie",IFERROR(VALUE(LEFT(I80,FIND(" ",I80)-1)),""),"") -> 103 | O80: =IF(B80="TV Show",IFERROR(VALUE(LEFT(I80,FIND(" ",I80)-1)),""),"") | P80: =IF(K80="","",K80-G80) -> 0
A81: 80182115 | B81: Movie | C81: Long Shot | D81: Jacob LaMendola | E81: United States | F81: September 29, 2017 | G81: 2017 | H81: TV-14 | I81: 40 min | J81: Documentaries | K81: =IFERROR(VALUE(RIGHT(TRIM(F81),4)),"") -> 2017 | L81: =IF(TRIM(E81)="","Unknown",IFERROR(LEFT(TRIM(E81),FIND(",",TRIM(E81))-1),TRIM(E81))) -> United States | M81: =IFERROR(LEFT(J81,FIND(",",J81)-1),J81) -> Documentaries | N81: =IF(B81="Movie",IFERROR(VALUE(LEFT(I81,FIND(" ",I81)-1)),""),"") -> 40 | O81: =IF(B81="TV Show",IFERROR(VALUE(LEFT(I81,FIND(" ",I81)-1)),""),"") | P81: =IF(K81="","",K81-G81) -> 0
A82: 80163293 | B82: TV Show | C82: Mak Cun | F82: September 29, 2017 | G82: 2015 | H82: TV-PG | I82: 1 Season | J82: International TV Shows, TV Comedies, TV Dramas | K82: =IFERROR(VALUE(RIGHT(TRIM(F82),4)),"") -> 2017 | L82: =IF(TRIM(E82)="","Unknown",IFERROR(LEFT(TRIM(E82),FIND(",",TRIM(E82))-1),TRIM(E82))) -> Unknown | M82: =IFERROR(LEFT(J82,FIND(",",J82)-1),J82) -> International TV Shows | N82: =IF(B82="Movie",IFERROR(VALUE(LEFT(I82,FIND(" ",I82)-1)),""),"") | O82: =IF(B82="TV Show",IFERROR(VALUE(LEFT(I82,FIND(" ",I82)-1)),""),"") -> 1 | P82: =IF(K82="","",K82-G82) -> 2
A83: 80104068 | B83: Movie | C83: Our Souls at Night | D83: Ritesh Batra | E83: United States | F83: September 29, 2017 | G83: 2017 | H83: TV-14 | I83: 103 min | J83: Dramas, Romantic Movies | K83: =IFERROR(VALUE(RIGHT(TRIM(F83),4)),"") -> 2017 | L83: =IF(TRIM(E83)="","Unknown",IFERROR(LEFT(TRIM(E83),FIND(",",TRIM(E83))-1),TRIM(E83))) -> United States | M83: =IFERROR(LEFT(J83,FIND(",",J83)-1),J83) -> Dramas | N83: =IF(B83="Movie",IFERROR(VALUE(LEFT(I83,FIND(" ",I83)-1)),""),"") -> 103 | O83: =IF(B83="TV Show",IFERROR(VALUE(LEFT(I83,FIND(" ",I83)-1)),""),"") | P83: =IF(K83="","",K83-G83) -> 0
A84: 80119349 | B84: Movie | C84: Out of Thin Air | D84: Dylan Howitt | F84: September 29, 2017 | G84: 2017 | H84: TV-14 | I84: 85 min | J84: Documentaries, International Movies | K84: =IFERROR(VALUE(RIGHT(TRIM(F84),4)),"") -> 2017 | L84: =IF(TRIM(E84)="","Unknown",IFERROR(LEFT(TRIM(E84),FIND(",",TRIM(E84))-1),TRIM(E84))) -> Unknown | M84: =IFERROR(LEFT(J84,FIND(",",J84)-1),J84) -> Documentaries | N84: =IF(B84="Movie",IFERROR(VALUE(LEFT(I84,FIND(" ",I84)-1)),""),"") -> 85 | O84: =IF(B84="TV Show",IFERROR(VALUE(LEFT(I84,FIND(" ",I84)-1)),""),"") | P84: =IF(K84="","",K84-G84) -> 0
A85: 80199032 | B85: TV Show | C85: Paul Hollywood's Big Continental Road Trip | E85: United Kingdom | F85: September 29, 2017 | G85: 2017 | H85: TV-14 | I85: 1 Season | J85: British TV Shows, Docuseries, International TV Shows | K85: =IFERROR(VALUE(RIGHT(TRIM(F85),4)),"") -> 2017 | L85: =IF(TRIM(E85)="","Unknown",IFERROR(LEFT(TRIM(E85),FIND(",",TRIM(E85))-1),TRIM(E85))) -> United Kingdom | M85: =IFERROR(LEFT(J85,FIND(",",J85)-1),J85) -> British TV Shows | N85: =IF(B85="Movie",IFERROR(VALUE(LEFT(I85,FIND(" ",I85)-1)),""),"") | O85: =IF(B85="TV Show",IFERROR(VALUE(LEFT(I85,FIND(" ",I85)-1)),""),"") -> 1 | P85: =IF(K85="","",K85-G85) -> 0
A86: 80180449 | B86: TV Show | C86: Satu Hari | F86: September 29, 2017 | G86: 2014 | H86: TV-14 | I86: 1 Season | J86: International TV Shows, TV Dramas | K86: =IFERROR(VALUE(RIGHT(TRIM(F86),4)),"") -> 2017 | L86: =IF(TRIM(E86)="","Unknown",IFERROR(LEFT(TRIM(E86),FIND(",",TRIM(E86))-1),TRIM(E86))) -> Unknown | M86: =IFERROR(LEFT(J86,FIND(",",J86)-1),J86) -> International TV Shows | N86: =IF(B86="Movie",IFERROR(VALUE(LEFT(I86,FIND(" ",I86)-1)),""),"") | O86: =IF(B86="TV Show",IFERROR(VALUE(LEFT(I86,FIND(" ",I86)-1)),""),"") -> 1 | P86: =IF(K86="","",K86-G86) -> 3
A87: 80019931 | B87: Movie | C87: Monster High: Boo York, Boo York | D87: William Lau | E87: United States | F87: September 29, 2015 | G87: 2015 | H87: TV-Y7 | I87: 72 min | J87: Children & Family Movies, Music & Musicals | K87: =IFERROR(VALUE(RIGHT(TRIM(F87),4)),"") -> 2015 | L87: =IF(TRIM(E87)="","Unknown",IFERROR(LEFT(TRIM(E87),FIND(",",TRIM(E87))-1),TRIM(E87))) -> United States | M87: =IFERROR(LEFT(J87,FIND(",",J87)-1),J87) -> Children & Family Movies | N87: =IF(B87="Movie",IFERROR(VALUE(LEFT(I87,FIND(" ",I87)-1)),""),"") -> 72 | O87: =IF(B87="TV Show",IFERROR(VALUE(LEFT(I87,FIND(" ",I87)-1)),""),"") | P87: =IF(K87="","",K87-G87) -> 0
A88: 81053893 | B88: Movie | C88: Cultivating the Seas: History and Future of the Full-Cycle Cultured Kindai Tuna | D88: Mana Yasuda | F88: September 28, 2019 | G88: 2019 | H88: TV-G | I88: 45 min | J88: Documentaries, International Movies | K88: =IFERROR(VALUE(RIGHT(TRIM(F88),4)),"") -> 2019 | L88: =IF(TRIM(E88)="","Unknown",IFERROR(LEFT(TRIM(E88),FIND(",",TRIM(E88))-1),TRIM(E88))) -> Unknown | M88: =IFERROR(LEFT(J88,FIND(",",J88)-1),J88) -> Documentaries | N88: =IF(B88="Movie",IFERROR(VALUE(LEFT(I88,FIND(" ",I88)-1)),""),"") -> 45 | O88: =IF(B88="TV Show",IFERROR(VALUE(LEFT(I88,FIND(" ",I88)-1)),""),"") | P88: =IF(K88="","",K88-G88) -> 0
A89: 80200087 | B89: Movie | C89: Domino | D89: Brian De Palma | E89: Denmark, France, Italy, Belgium, Netherlands | F89: September 28, 2019 | G89: 2019 | H89: R | I89: 89 min | J89: International Movies, Thrillers | K89: =IFERROR(VALUE(RIGHT(TRIM(F89),4)),"") -> 2019 | L89: =IF(TRIM(E89)="","Unknown",IFERROR(LEFT(TRIM(E89),FIND(",",TRIM(E89))-1),TRIM(E89))) -> Denmark | M89: =IFERROR(LEFT(J89,FIND(",",J89)-1),J89) -> International Movies | N89: =IF(B89="Movie",IFERROR(VALUE(LEFT(I89,FIND(" ",I89)-1)),""),"") -> 89 | O89: =IF(B89="TV Show",IFERROR(VALUE(LEFT(I89,FIND(" ",I89)-1)),""),"") | P89: =IF(K89="","",K89-G89) -> 0
A90: 81053892 | B90: Movie | C90: TUNA GIRL | D90: Mana Yasuda | F90: September 28, 2019 | G90: 2019 | H90: TV-PG | I90: 90 min | J90: Dramas, International Movies | K90: =IFERROR(VALUE(RIGHT(TRIM(F90),4)),"") -> 2019 | L90: =IF(TRIM(E90)="","Unknown",IFERROR(LEFT(TRIM(E90),FIND(",",TRIM(E90))-1),TRIM(E90))) -> Unknown | M90: =IFERROR(LEFT(J90,FIND(",",J90)-1),J90) -> Dramas | N90: =IF(B90="Movie",IFERROR(VALUE(LEFT(I90,FIND(" ",I90)-1)),""),"") -> 90 | O90: =IF(B90="TV Show",IFERROR(VALUE(LEFT(I90,FIND(" ",I90)-1)),""),"") | P90: =IF(K90="","",K90-G90) -> 0
A91: 81002850 | B91: Movie | C91: 5CM | D91: Rizal Mantovani | E91: Indonesia | F91: September 28, 2018 | G91: 2012 | H91: TV-14 | I91: 126 min | J91: Dramas, International Movies | K91: =IFERROR(VALUE(RIGHT(TRIM(F91),4)),"") -> 2018 | L91: =IF(TRIM(E91)="","Unknown",IFERROR(LEFT(TRIM(E91),FIND(",",TRIM(E91))-1),TRIM(E91))) -> Indonesia | M91: =IFERROR(LEFT(J91,FIND(",",J91)-1),J91) -> Dramas | N91: =IF(B91="Movie",IFERROR(VALUE(LEFT(I91,FIND(" ",I91)-1)),""),"") -> 126 | O91: =IF(B91="TV Show",IFERROR(VALUE(LEFT(I91,FIND(" ",I91)-1)),""),"") | P91: =IF(K91="","",K91-G91) -> 6
A92: 81004470 | B92: Movie | C92: Animal World | D92: Han Yan | E92: China | F92: September 28, 2018 | G92: 2018 | H92: TV-MA | I92: 130 min | J92: Action & Adventure, International Movies, Sci-Fi & Fantasy | K92: =IFERROR(VALUE(RIGHT(TRIM(F92),4)),"") -> 2018 | L92: =IF(TRIM(E92)="","Unknown",IFERROR(LEFT(TRIM(E92),FIND(",",TRIM(E92))-1),TRIM(E92))) -> China | M92: =IFERROR(LEFT(J92,FIND(",",J92)-1),J92) -> Action & Adventure | N92: =IF(B92="Movie",IFERROR(VALUE(LEFT(I92,FIND(" ",I92)-1)),""),"") -> 130 | O92: =IF(B92="TV Show",IFERROR(VALUE(LEFT(I92,FIND(" ",I92)-1)),""),"") | P92: =IF(K92="","",K92-G92) -> 0
A93: 80157072 | B93: Movie | C93: Hold the Dark | D93: Jeremy Saulnier | E93: United States | F93: September 28, 2018 | G93: 2018 | H93: TV-MA | I93: 126 min | J93: Action & Adventure, Dramas | K93: =IFERROR(VALUE(RIGHT(TRIM(F93),4)),"") -> 2018 | L93: =IF(TRIM(E93)="","Unknown",IFERROR(LEFT(TRIM(E93),FIND(",",TRIM(E93))-1),TRIM(E93))) -> United States | M93: =IFERROR(LEFT(J93,FIND(",",J93)-1),J93) -> Action & Adventure | N93: =IF(B93="Movie",IFERROR(VALUE(LEFT(I93,FIND(" ",I93)-1)),""),"") -> 126 | O93: =IF(B93="TV Show",IFERROR(VALUE(LEFT(I93,FIND(" ",I93)-1)),""),"") | P93: =IF(K93="","",K93-G93) -> 0
A94: 81001809 | B94: Movie | C94: Lessons from a School Shooting: Notes from Dunblane | D94: Kim A. Snyder | E94: United States | F94: September 28, 2018 | G94: 2018 | H94: TV-PG | I94: 24 min | J94: Documentaries | K94: =IFERROR(VALUE(RIGHT(TRIM(F94),4)),"") -> 2018 | L94: =IF(TRIM(E94)="","Unknown",IFERROR(LEFT(TRIM(E94),FIND(",",TRIM(E94))-1),TRIM(E94))) -> United States | M94: =IFERROR(LEFT(J94,FIND(",",J94)-1),J94) -> Documentaries | N94: =IF(B94="Movie",IFERROR(VALUE(LEFT(I94,FIND(" ",I94)-1)),""),"") -> 24 | O94: =IF(B94="TV Show",IFERROR(VALUE(LEFT(I94,FIND(" ",I94)-1)),""),"") | P94: =IF(K94="","",K94-G94) -> 0
A95: 80201933 | B95: TV Show | C95: Made in Mexico | E95: United States | F95: September 28, 2018 | G95: 2018 | H95: TV-MA | I95: 1 Season | J95: International TV Shows, Reality TV, Spanish-Language TV Shows | K95: =IFERROR(VALUE(RIGHT(TRIM(F95),4)),"") -> 2018 | L95: =IF(TRIM(E95)="","Unknown",IFERROR(LEFT(TRIM(E95),FIND(",",TRIM(E95))-1),TRIM(E95))) -> United States | M95: =IFERROR(LEFT(J95,FIND(",",J95)-1),J95) -> International TV Shows | N95: =IF(B95="Movie",IFERROR(VALUE(LEFT(I95,FIND(" ",I95)-1)),""),"") | O95: =IF(B95="TV Show",IFERROR(VALUE(LEFT(I95,FIND(" ",I95)-1)),""),"") -> 1 | P95: =IF(K95="","",K95-G95) -> 0
A96: 81002864 | B96: Movie | C96: Single | D96: Raditya Dika | E96: Indonesia | F96: September 28, 2018 | G96: 2015 | H96: TV-PG | I96: 127 min | J96: Comedies, International Movies, Romantic Movies | K96: =IFERROR(VALUE(RIGHT(TRIM(F96),4)),"") -> 2018 | L96: =IF(TRIM(E96)="","Unknown",IFERROR(LEFT(TRIM(E96),FIND(",",TRIM(E96))-1),TRIM(E96))) -> Indonesia | M96: =IFERROR(LEFT(J96,FIND(",",J96)-1),J96) -> Comedies | N96: =IF(B96="Movie",IFERROR(VALUE(LEFT(I96,FIND(" ",I96)-1)),""),"") -> 127 | O96: =IF(B96="TV Show",IFERROR(VALUE(LEFT(I96,FIND(" ",I96)-1)),""),"") | P96: =IF(K96="","",K96-G96) -> 3
A97: 81016750 | B97: Movie | C97: The 3rd Eye | D97: Rocky Soraya | E97: Indonesia | F97: September 28, 2018 | G97: 2018 | H97: TV-MA | I97: 108 min | J97: Horror Movies, International Movies | K97: =IFERROR(VALUE(RIGHT(TRIM(F97),4)),"") -> 2018 | L97: =IF(TRIM(E97)="","Unknown",IFERROR(LEFT(TRIM(E97),FIND(",",TRIM(E97))-1),TRIM(E97))) -> Indonesia | M97: =IFERROR(LEFT(J97,FIND(",",J97)-1),J97) -> Horror Movies | N97: =IF(B97="Movie",IFERROR(VALUE(LEFT(I97,FIND(" ",I97)-1)),""),"") -> 108 | O97: =IF(B97="TV Show",IFERROR(VALUE(LEFT(I97,FIND(" ",I97)-1)),""),"") | P97: =IF(K97="","",K97-G97) -> 0
A98: 81002866 | B98: Movie | C98: The Sinking Of Van Der Wijck | D98: Sunil Soraya | E98: Indonesia | F98: September 28, 2018 | G98: 2013 | H98: TV-14 | I98: 163 min | J98: Dramas, International Movies, Romantic Movies | K98: =IFERROR(VALUE(RIGHT(TRIM(F98),4)),"") -> 2018 | L98: =IF(TRIM(E98)="","Unknown",IFERROR(LEFT(TRIM(E98),FIND(",",TRIM(E98))-1),TRIM(E98))) -> Indonesia | M98: =IFERROR(LEFT(J98,FIND(",",J98)-1),J98) -> Dramas | N98: =IF(B98="Movie",IFERROR(VALUE(LEFT(I98,FIND(" ",I98)-1)),""),"") -> 163 | O98: =IF(B98="TV Show",IFERROR(VALUE(LEFT(I98,FIND(" ",I98)-1)),""),"") | P98: =IF(K98="","",K98-G98) -> 5
A99: 80992039 | B99: Movie | C99: Two Catalonias | D99: Álvaro Longoria, Gerardo Olivares | E99: Spain | F99: September 28, 2018 | G99: 2018 | H99: TV-MA | I99: 117 min | J99: Documentaries, International Movies | K99: =IFERROR(VALUE(RIGHT(TRIM(F99),4)),"") -> 2018 | L99: =IF(TRIM(E99)="","Unknown",IFERROR(LEFT(TRIM(E99),FIND(",",TRIM(E99))-1),TRIM(E99))) -> Spain | M99: =IFERROR(LEFT(J99,FIND(",",J99)-1),J99) -> Documentaries | N99: =IF(B99="Movie",IFERROR(VALUE(LEFT(I99,FIND(" ",I99)-1)),""),"") -> 117 | O99: =IF(B99="TV Show",IFERROR(VALUE(LEFT(I99,FIND(" ",I99)-1)),""),"") | P99: =IF(K99="","",K99-G99) -> 0
A100: 80126507 | B100: Movie | C100: Bobby Sands: 66 Days | D100: Brendan Byrne | E100: Ireland, United Kingdom | F100: September 28, 2017 | G100: 2016 | H100: TV-14 | I100: 106 min | J100: Documentaries | K100: =IFERROR(VALUE(RIGHT(TRIM(F100),4)),"") -> 2017 | L100: =IF(TRIM(E100)="","Unknown",IFERROR(LEFT(TRIM(E100),FIND(",",TRIM(E100))-1),TRIM(E100))) -> Ireland | M100: =IFERROR(LEFT(J100,FIND(",",J100)-1),J100) -> Documentaries | N100: =IF(B100="Movie",IFERROR(VALUE(LEFT(I100,FIND(" ",I100)-1)),""),"") -> 106 | O100: =IF(B100="TV Show",IFERROR(VALUE(LEFT(I100,FIND(" ",I100)-1)),""),"") | P100: =IF(K100="","",K100-G100) -> 1
...
